{
"panelUID":"ell","panelName":"East London Line","panelDescription":"Highbury & Islington - New Cross & New Cross Gate","areas":["NX","U3","X1","X3","Y9"],
"berths":[
{"x":1034,"y":250,"i":["NX0203"]},
{"x":1034,"y":282,"i":["NXF205"]},
{"x":978,"y":282,"i":["NXR205"]},
{"x":1146,"y":314,"i":["NX0206"]},
{"x":1034,"y":314,"i":["NXF207"]},
{"x":978,"y":314,"i":["NXR207"]},
{"x":1146,"y":282,"i":["NX0208"]},
{"x":1034,"y":346,"i":["NX0209"]},
{"x":1370,"y":314,"i":["NX0210"]},
{"x":1210,"y":282,"i":["NX0211"]},
{"x":1434,"y":314,"i":["NX0212"]},
{"x":1210,"y":314,"i":["NX0213"]},
{"x":1498,"y":314,"i":["NX0214"]},
{"x":1306,"y":282,"i":["NX0215"]},
{"x":1562,"y":314,"i":["NX0216"]},
{"x":1370,"y":282,"i":["NX0217"]},
{"x":1626,"y":314,"i":["NX0218"]},
{"x":1690,"y":314,"i":["NX0220"]},
{"x":1434,"y":282,"i":["NX0221"]},
{"x":1754,"y":314,"i":["NX0222"]},
{"x":1498,"y":282,"i":["NX0223"]},
{"x":1818,"y":314,"i":["NX0224"]},
{"x":1562,"y":282,"i":["NX0225"]},
{"x":1882,"y":314,"i":["NX0226"]},
{"x":1626,"y":282,"i":["NX0227"]},
{"x":1946,"y":314,"i":["NX0228"]},
{"x":1690,"y":282,"i":["NX0229"]},
{"x":2010,"y":314,"i":["NX0230"]},
{"x":1754,"y":282,"i":["NX0231"]},
{"x":2090,"y":314,"i":["NX0232"]},
{"x":1818,"y":282,"i":["NX0233"]},
{"x":2154,"y":314,"i":["NX0234"]},
{"x":1914,"y":282,"i":["NX0235"]},
{"x":2010,"y":282,"i":["NX0237"]},
{"x":2218,"y":314,"i":["NX0238","NX3001"]},
{"x":2090,"y":282,"i":["NX0239"]},
{"x":2314,"y":314,"i":["NX0240"]},
{"x":2154,"y":282,"i":["NX0241"]},
{"x":2314,"y":282,"i":["NX0242"]},
{"x":2218,"y":282,"i":["NX0243"]},
{"x":2442,"y":314,"i":["NX0244"]},
{"x":2378,"y":282,"i":["NX0245"]},
{"x":2506,"y":314,"i":["NX0246"]},
{"x":2378,"y":314,"i":["NX0247"]},
{"x":2570,"y":314,"i":["NX0248"]},
{"x":2474,"y":282,"i":["NX0249"]},
{"x":2634,"y":314,"i":["NX0250"]},
{"x":2570,"y":282,"i":["NX0251"]},
{"x":2698,"y":314,"i":["NX0252"]},
{"x":2634,"y":282,"i":["NX0253"]},
{"x":2794,"y":314,"i":["NX0254"]},
{"x":2698,"y":282,"i":["NX0255"]},
{"x":2794,"y":282,"i":["NX0256"]},
{"x":2858,"y":282,"i":["NX0257"]},
{"x":2954,"y":314,"i":["NX0258"]},
{"x":2858,"y":314,"i":["NX0259"]},
{"x":3034,"y":314,"i":["NX0260"]},
{"x":2954,"y":282,"i":["NX0261"]},
{"x":3098,"y":314,"i":["NX0262"]},
{"x":3034,"y":282,"i":["NX0263"]},
{"x":3202,"y":314,"i":["NX0264"]},
{"x":3202,"y":282,"i":["NX0265"]},
{"x":3386,"y":314,"i":["NX0266"]},
{"x":3322,"y":282,"i":["NX0267"]},
{"x":3466,"y":530,"i":["NX0268"]},
{"x":3514,"y":282,"i":["NX0269"]},
{"x":3658,"y":282,"i":["NX0271"]},
{"x":3298,"y":346,"i":["NX0273"]},
{"x":3498,"y":470,"i":["NX0280"]},
{"x":3514,"y":314,"i":["NX0281"]},
{"x":3530,"y":422,"i":["NX0282"]},
{"x":3658,"y":314,"i":["NX0283"]},
{"x":3530,"y":398,"i":["NX0284"]},
{"x":3706,"y":346,"i":["NX0285"]},
{"x":3530,"y":374,"i":["NX0286"]},
{"x":3466,"y":106,"i":["NX0287"]},
{"x":3530,"y":346,"i":["NX0288"]},
{"x":3466,"y":138,"i":["NX0290"]},
{"x":3594,"y":138,"i":["NXF294"]},
{"x":3650,"y":138,"i":["NXR294"]},
{"x":3594,"y":314,"i":["NX0296"]},
{"x":3778,"y":346,"i":["NXF298"]},
{"x":3834,"y":346,"i":["NXR298"]},
{"x":3882,"y":314,"i":["NX0300"]},
{"x":218,"y":282,"i":["NX0318"]},
{"x":362,"y":282,"i":["NX0320"]},
{"x":362,"y":314,"i":["NX0322"]},
{"x":490,"y":314,"i":["NX0324"]},
{"x":282,"y":314,"i":["NXF325"]},
{"x":218,"y":314,"i":["NXR325"]},
{"x":554,"y":314,"i":["NX0326"]},
{"x":282,"y":282,"i":["NX0327"]},
{"x":442,"y":282,"i":["NX0329"]},
{"x":682,"y":314,"i":["NX0330"]},
{"x":746,"y":314,"i":["NX0332"]},
{"x":554,"y":282,"i":["NX0333"]},
{"x":810,"y":314,"i":["NX0334"]},
{"x":618,"y":282,"i":["NX0335"]},
{"x":970,"y":250,"i":["NX0336"]},
{"x":682,"y":282,"i":["NX0337"]},
{"x":970,"y":346,"i":["NX0338"]},
{"x":746,"y":282,"i":["NX0339"]},
{"x":3090,"y":410,"i":["NX0350"]},
{"x":3090,"y":442,"i":["NX0351"]},
{"x":3026,"y":410,"i":["NX0352"]},
{"x":3026,"y":442,"i":["NX0353"]},
{"x":2914,"y":410,"i":["NX0354"]},
{"x":3298,"y":314,"i":["NX3005"]},
{"x":3482,"y":622,"i":["NX3006"]},
{"x":3626,"y":622,"i":["NX3008"]},
{"x":3402,"y":594,"i":["NX3007"]},
{"x":3402,"y":622,"i":["NX3009"]},
{"x":3402,"y":650,"i":["NX3011"]},
{"x":3402,"y":678,"i":["NX3013"]},
{"x":3594,"y":346,"i":["NX3015"]},
{"x":3610,"y":374,"i":["NX3017"]},
{"x":3610,"y":398,"i":["NX3019"]},
{"x":3610,"y":422,"i":["NX3021"]},
{"x":3610,"y":446,"i":["NX3023"]},
{"x":3530,"y":446,"i":["NXRSD4"]},
{"x":3594,"y":470,"i":["NX3025"]},
{"x":3594,"y":494,"i":["NX3027"]},
{"x":3594,"y":518,"i":["NX3029"]},
{"x":3594,"y":542,"i":["NX3031"]},
{"x":3594,"y":566,"i":["NX3033"]},
{"x":3594,"y":590,"i":["NX3035"]},
{"x":3562,"y":622,"i":["NX3037"]},
{"x":3218,"y":346,"i":["NX3051"]},
{"x":3218,"y":374,"i":["NX3053"]},
{"x":3202,"y":402,"i":["NX3055"]},
{"x":3202,"y":430,"i":["NX3057"]},
{"x":3202,"y":458,"i":["NX3059"]},
{"x":3202,"y":486,"i":["NX3061"]},
{"x":3202,"y":514,"i":["NX3063"]},
{"x":3202,"y":542,"i":["NX3065"]},
{"x":3202,"y":570,"i":["NX3067"]},
{"x":3202,"y":598,"i":["NX3069"]},
{"x":154,"y":250,"i":["U31234"]},
{"x":282,"y":250,"i":["U31239"]},
{"x":218,"y":250,"i":["U31242"]},
{"x":346,"y":154,"i":["U31243"]},
{"x":218,"y":218,"i":["U31244"]},
{"x":282,"y":218,"i":["U31245"]},
{"x":362,"y":250,"i":["U31246"]},
{"x":554,"y":218,"i":["U31247"]},
{"x":490,"y":250,"i":["U31250"]},
{"x":682,"y":218,"i":["U31251"]},
{"x":554,"y":250,"i":["U31254"]},
{"x":682,"y":250,"i":["U31256","U31253"]},
{"x":746,"y":250,"i":["U31258"]},
{"x":154,"y":218,"i":["U31311"]},
{"x":442,"y":218,"i":["U31315"]},
{"x":618,"y":218,"i":["U31317"]},
{"x":2962,"y":442,"i":["X10615"]},
{"x":3882,"y":474,"i":["X14018"]},
{"x":3946,"y":378,"i":["X14027"]},
{"x":3882,"y":442,"i":["X14446"]},
{"x":3946,"y":410,"i":["X14455"]},
{"x":3946,"y":314,"i":["X14629"],"td":"NX"},
{"x":3882,"y":378,"i":["X15130"]},
{"x":3882,"y":410,"i":["X15132"]},
{"x":3946,"y":474,"i":["X15139"]},
{"x":3946,"y":442,"i":["X15141"]},
{"x":3594,"y":202,"i":["X32444"]},
{"x":3658,"y":202,"i":["X32451"]},
{"x":3594,"y":234,"i":["X32546"]},
{"x":3658,"y":170,"i":["X32559"]},
{"x":282,"y":154,"i":["Y90375"]}
],
"signals":[
{"x":1034,"y":242,"d":"L203TRS","i":["NX29:1"],"t":"TEXT","1":"TRTS>"},
{"x":1034,"y":298,"d":"L205TRS","i":["NX29:2"],"t":"TEXT","1":"TRTS>"},
{"x":1034,"y":306,"d":"L207TRS","i":["NX29:3"],"t":"TEXT","1":"TRTS>"},
{"x":1034,"y":362,"d":"L209TRS","i":["NX29:4"],"t":"TEXT","1":"TRTS>"},
{"x":2332,"y":306,"d":"L240TRS","i":["NX29:5"],"t":"TEXT","1":"<TRTS","isDev":1},
{"x":2332,"y":298,"d":"L242TRS","i":["NX29:6"],"t":"TEXT","1":"<TRTS","isDev":1},
{"x":2858,"y":298,"d":"L257TRS","i":["NX29:7"],"t":"TEXT","1":"TRTS>","isDev":1},
{"x":2858,"y":306,"d":"L259TRS","i":["NX29:8"],"t":"TEXT","1":"TRTS>","isDev":1},
{"x":3900,"y":306,"d":"L300TRS","i":["NX2A:1"],"t":"TEXT","1":"<TRTS"},
{"x":282,"y":306,"d":"L325TRS","i":["NX2A:2"],"t":"TEXT","1":"TRTS>"},
{"x":1092,"y":246,"d":"EL203","i":"$_EL203_M","t":"NONE"},
{"x":1084,"y":246,"d":"EL203","i":"$_EL203_P","t":"LEFT","r":["NX0D:1","NX0D:2"],"iSu":1,"f":["$_EL203_P"]},
{"x":1094,"y":278,"d":"EL205","i":"$_EL205_M","t":"NONE"},
{"x":1086,"y":278,"d":"EL205","i":"$_EL205_P","t":"LEFT","r":["NX0D:3","NX0D:4","NX0D:5","NX0D:6"],"iSu":1,"f":["$_EL205_P"]},
{"x":1136,"y":334,"d":"EL206","i":"$_EL206_M","t":"NONE"},
{"x":1144,"y":334,"d":"EL206","i":"$_EL206_P","t":"RIGHT","r":["NX0D:8","NX0E:1","NX0E:2","NX0E:3","NX0E:4","NX0E:5"],"iSu":1,"f":["$_EL206_P"]},
{"x":1094,"y":334,"d":"EL207","i":"$_EL207_M","t":"NONE"},
{"x":1086,"y":334,"d":"EL207","i":"$_EL207_P","t":"LEFT","r":["NX0E:6","NX0E:7","NX0E:8","NX0F:1"],"iSu":1,"f":["$_EL207_P"]},
{"x":1136,"y":278,"d":"EL208","i":"$_EL208_M","t":"NONE"},
{"x":1144,"y":278,"d":"EL208","i":"$_EL208_P","t":"RIGHT","r":["NX0F:2","NX0F:3","NX0F:4","NX0F:5","NX0F:6","NX0F:7"],"iSu":1,"f":["$_EL208_P"]},
{"x":1094,"y":342,"d":"EL209","i":"$_EL209_M","t":"NONE"},
{"x":1086,"y":342,"d":"EL209","i":"$_EL209_P","t":"LEFT","r":["NX0F:8","NX10:1"],"iSu":1,"f":["$_EL209_P"]},
{"x":1358,"y":334,"d":"EL210","i":"$_EL210_M","t":"NONE"},
{"x":1366,"y":334,"d":"EL210","i":"$_EL210_P","t":"RIGHT","r":["NX10:2","NX10:3","NX10:4","NX10:5"],"iSu":1,"f":["$_EL210_P"]},
{"x":1268,"y":278,"d":"EL211","i":"$_EL211_M","t":"NONE"},
{"x":1260,"y":278,"d":"EL211","i":"$_EL211_P","t":"LEFT","r":["NX10:6","NX10:7"],"iSu":1,"f":["$_EL211_P"]},
{"x":1432,"y":334,"d":"EL212","i":"NX01:1","t":"RIGHT"},
{"x":1268,"y":334,"d":"EL213","i":"$_EL213_M","t":"NONE"},
{"x":1260,"y":334,"d":"EL213","i":"$_EL213_P","t":"LEFT","r":["NX10:8","NX11:1"],"iSu":1,"f":["$_EL213_P"]},
{"x":1496,"y":334,"d":"EL214","i":"NX01:3","t":"RIGHT"},
{"x":1356,"y":278,"d":"EL215","i":"NX01:4","t":"LEFT"},
{"x":1558,"y":334,"d":"EL216","i":"NX01:5","t":"RIGHT"},
{"x":1422,"y":278,"d":"EL217","i":"NX01:6","t":"LEFT"},
{"x":1624,"y":334,"d":"EL218","i":"NX01:7","t":"RIGHT"},
{"x":1688,"y":334,"d":"EL220","i":"NX01:8","t":"RIGHT"},
{"x":1484,"y":278,"d":"EL221","i":"NX02:1","t":"LEFT"},
{"x":1752,"y":334,"d":"EL222","i":"NX02:2","t":"RIGHT"},
{"x":1548,"y":278,"d":"EL223","i":"NX02:3","t":"LEFT"},
{"x":1816,"y":334,"d":"EL224","i":"NX02:4","t":"RIGHT"},
{"x":1614,"y":278,"d":"EL225","i":"NX02:5","t":"LEFT"},
{"x":1880,"y":334,"d":"EL226","i":"NX02:6","t":"RIGHT"},
{"x":1676,"y":278,"d":"EL227","i":"NX02:7","t":"LEFT"},
{"x":1944,"y":334,"d":"EL228","i":"NX02:8","t":"RIGHT"},
{"x":1740,"y":278,"d":"EL229","i":"NX03:1","t":"LEFT"},
{"x":2008,"y":310,"d":"EL230","i":"NX03:2","t":"RIGHT"},
{"x":2040,"y":310,"d":"EL230BR","i":"NX03:2","t":"RIGHT","iBa":1},
{"x":1804,"y":278,"d":"EL231","i":"NX03:3","t":"LEFT"},
{"x":2088,"y":334,"d":"EL232","i":"NX03:4","t":"RIGHT"},
{"x":1870,"y":278,"d":"EL233","i":"NX03:5","t":"LEFT"},
{"x":2152,"y":310,"d":"EL234","i":"NX03:6","t":"RIGHT"},
{"x":2184,"y":310,"d":"EL234BR","i":"NX03:6","t":"RIGHT","iBa":1},
{"x":1964,"y":278,"d":"EL235","i":"NX03:7","t":"LEFT"},
{"x":2060,"y":302,"d":"EL237","i":"NX03:8","t":"LEFT"},
{"x":2216,"y":334,"d":"EL238","i":"NX04:1","t":"RIGHT"},
{"x":2248,"y":310,"d":"EL238BR","i":"NX04:1","t":"RIGHT","iBa":1},
{"x":2142,"y":278,"d":"EL239","i":"NX04:2","t":"LEFT"},
{"x":2102,"y":302,"d":"EL239BR","i":"NX04:2","t":"LEFT","iBa":1},
{"x":2302,"y":334,"d":"EL240","i":"$_EL240_M","t":"NONE"},
{"x":2310,"y":334,"d":"EL240","i":"$_EL240_S","t":"RIGHT","r":["NX11:2","NX11:3","NX11:4"],"iSu":1,"f":["$_EL240_P"]},
{"x":2204,"y":278,"d":"EL241","i":"NX04:4","t":"LEFT","r":["NX11:5"]},
{"x":2302,"y":278,"d":"EL242","i":"$_EL242_M","t":"NONE"},
{"x":2310,"y":278,"d":"EL242","i":"$_EL242_P","t":"RIGHT","r":["NX11:6","NX11:7"],"iSu":1,"f":["$_EL242_P"]},
{"x":2276,"y":278,"d":"EL243","i":"$_EL243_M","t":"NONE"},
{"x":2268,"y":278,"d":"EL243","i":"$_EL243_P","t":"LEFT","r":["NX11:8","NX12:1","NX12:2","NX12:3"],"iSu":1,"f":["$_EL243_P"]},
{"x":2440,"y":334,"d":"EL244","i":"NX04:7","t":"RIGHT","r":["NX12:4"]},
{"x":2430,"y":278,"d":"EL245","i":"NX04:8","t":"LEFT"},
{"x":2504,"y":334,"d":"EL246","i":"NX05:1","t":"RIGHT","r":["NX12:5"]},
{"x":2430,"y":334,"d":"EL247","i":"NX05:2","t":"LEFT"},
{"x":2566,"y":334,"d":"EL248","i":"NX05:3","t":"RIGHT"},
{"x":2524,"y":278,"d":"EL249","i":"NX05:4","t":"LEFT"},
{"x":2632,"y":334,"d":"EL250","i":"NX05:5","t":"RIGHT"},
{"x":2620,"y":302,"d":"EL251","i":"NX05:6","t":"LEFT"},
{"x":2588,"y":302,"d":"EL251BR","i":"NX05:6","t":"LEFT","iBa":1},
{"x":2694,"y":334,"d":"EL252","i":"NX05:7","t":"RIGHT"},
{"x":2734,"y":310,"d":"EL252BR","i":"NX05:7","t":"RIGHT","iBa":1},
{"x":2684,"y":302,"d":"EL253","i":"NX05:8","t":"LEFT","r":["NX12:6"]},
{"x":2790,"y":334,"d":"EL254","i":"NX06:1","t":"RIGHT"},
{"x":2750,"y":278,"d":"EL255","i":"NX06:2","t":"LEFT","r":["NX12:7"]},
{"x":2790,"y":278,"d":"EL256","i":"NX06:3","t":"RIGHT"},
{"x":2918,"y":278,"d":"EL257","i":"$_EL257_M","t":"NONE"},
{"x":2910,"y":278,"d":"EL257","i":"$_EL257_S","t":"LEFT","r":["NX12:8","NX13:1","NX13:2"],"iSu":1,"f":["$_EL257_P"]},
{"x":2944,"y":334,"d":"EL258","i":"$_EL258_M","t":"NONE"},
{"x":2952,"y":334,"d":"EL258","i":"$_EL258_P","t":"RIGHT","r":["NX13:3","NX13:4","NX13:5","NX13:6"],"iSu":1,"f":["$_EL258_P"]},
{"x":2918,"y":334,"d":"EL259","i":"$_EL259_M","t":"NONE"},
{"x":2910,"y":334,"d":"EL259","i":"$_EL259_P","t":"LEFT","r":["NX13:7","NX13:8"],"iSu":1,"f":["$_EL259_P"]},
{"x":3030,"y":334,"d":"EL260","i":"NX06:7","t":"RIGHT","r":["NX14:1"]},
{"x":3004,"y":302,"d":"EL261","i":"NX06:8","t":"LEFT"},
{"x":3096,"y":334,"d":"EL262","i":"NX07:1","t":"RIGHT","r":["NX14:2"]},
{"x":3128,"y":334,"d":"EL262BR","i":"NX07:1","t":"RIGHT","iBa":1},
{"x":3094,"y":278,"d":"EL263","i":"$_EL263_M","t":"NONE"},
{"x":3086,"y":278,"d":"EL263","i":"$_EL263_P","t":"LEFT","r":["NX14:3","NX14:4","NX14:5","NX14:6"],"iSu":1,"f":["$_EL263_P"]},
{"x":3192,"y":334,"d":"EL264","i":"$_EL264_M","t":"NONE"},
{"x":3200,"y":334,"d":"EL264","i":"$_EL264_P","t":"RIGHT","r":["NX14:7","NX14:8"],"iSu":1,"f":["$_EL264_P"]},
{"x":3252,"y":278,"d":"EL265","i":"NX07:4","t":"LEFT","r":["NX15:1"]},
{"x":3376,"y":334,"d":"EL266","i":"$_EL266_M","t":"NONE"},
{"x":3384,"y":334,"d":"EL266","i":"$_EL266_P","t":"RIGHT","r":["NX15:2","NX15:3","NX15:4","NX15:5","NX15:6","NX15:7","NX15:8","NX16:1","NX16:2","NX16:3","NX16:4","NX16:5","NX16:6","NX16:7","NX16:8","NX17:1","NX17:2","NX17:3","NX17:4","NX17:5","NX17:6","NX17:7"],"iSu":1,"f":["$_EL266_P"]},
{"x":3380,"y":278,"d":"EL267","i":"$_EL267_M","t":"NONE"},
{"x":3372,"y":278,"d":"EL267","i":"$_EL267_S","t":"LEFT","r":["NX18:4","NX18:5","NX18:6","NX18:7","NX18:8","NX19:1","NX19:2","NX19:4","NX19:5","NX19:7"],"iSu":1,"f":["$_EL267_P"]},
{"x":3456,"y":550,"d":"EL268","i":"$_EL268_M","t":"NONE"},
{"x":3464,"y":550,"d":"EL268","i":"$_EL268_P","t":"RIGHT","r":["NX19:8","NX1A:1"],"iSu":1,"f":["$_EL268_P"]},
{"x":3564,"y":278,"d":"EL269","i":"NX07:8","t":"LEFT","r":["NX1A:2"]},
{"x":3560,"y":670,"d":"EL270","i":"$_EL268_M","t":"RIGHT","iRe":1},
{"x":3716,"y":278,"d":"EL271","i":"$_EL271_M","t":"NONE"},
{"x":3708,"y":278,"d":"EL271","i":"$_EL271_P","t":"LEFT","r":["NX1A:3","NX1A:4"],"iSu":1,"f":["$_EL271_P"]},
{"x":3356,"y":342,"d":"EL273","i":"$_EL273_M","t":"NONE"},
{"x":3348,"y":342,"d":"EL273","i":"$_EL273_S","t":"LEFT","r":["NX1A:5","NX1A:6","NX1A:7","NX1A:8","NX2A:5","NX2A:6","NX2B:1","NX2B:2","NX2B:5","NX2B:8","NX2C:3"],"iSu":1,"f":["$_EL273_P"]},
{"x":3486,"y":488,"d":"EL280","i":"$_EL280_M","t":"NONE"},
{"x":3494,"y":488,"d":"EL280","i":"$_EL280_P","t":"RIGHT","r":["NX1B:3","NX1B:4"],"iSu":1,"f":["$_EL280_P"]},
{"x":3572,"y":334,"d":"EL281","i":"$_EL281_M","t":"NONE"},
{"x":3564,"y":334,"d":"EL281","i":"$_EL281_P","t":"LEFT","r":["NX1B:5","NX1B:6","NX1B:7","NX1B:8"],"iSu":1,"f":["$_EL281_P"]},
{"x":3518,"y":440,"d":"EL282","i":"$_EL282_M","t":"NONE"},
{"x":3526,"y":440,"d":"EL282","i":"$_EL282_P","t":"RIGHT","r":["NX1C:1","NX1C:2"],"iSu":1,"f":["$_EL282_P"]},
{"x":3716,"y":334,"d":"EL283","i":"$_EL283_M","t":"NONE"},
{"x":3708,"y":334,"d":"EL283","i":"$_EL283_P","t":"LEFT","r":["NX1C:3","NX1C:4"],"iSu":1,"f":["$_EL283_P"]},
{"x":3518,"y":416,"d":"EL284","i":"$_EL284_M","t":"NONE"},
{"x":3526,"y":416,"d":"EL284","i":"$_EL284_P","t":"RIGHT","r":["NX1C:5","NX1C:6"],"iSu":1,"f":["$_EL284_P"]},
{"x":3764,"y":342,"d":"EL285","i":"$_EL285_M","t":"NONE"},
{"x":3756,"y":342,"d":"EL285","i":"$_EL285_P","t":"LEFT","r":["NX1C:7","NX1D:1","NX1D:2"],"iSu":1,"f":["$_EL285_P"]},
{"x":3518,"y":392,"d":"EL286","i":"$_EL286_M","t":"NONE"},
{"x":3526,"y":392,"d":"EL286","i":"$_EL286_S","t":"RIGHT","r":["NX1D:3","NX1D:4","NX1D:5","NX1D:6"],"iSu":1,"f":["$_EL286_P"]},
{"x":3524,"y":102,"d":"EL287","i":"$_EL287_M","t":"NONE"},
{"x":3516,"y":102,"d":"EL287","i":"$_EL287_P","t":"LEFT","r":["NX1D:7","NX1D:8"],"iSu":1,"f":["$_EL287_P"]},
{"x":3518,"y":364,"d":"EL288","i":"$_EL288_M","t":"NONE"},
{"x":3526,"y":364,"d":"EL288","i":"$_EL288_S","t":"RIGHT","r":["NX1E:1","NX1E:2","NX1E:3","NX1E:4"],"iSu":1,"f":["$_EL288_P"]},
{"x":3572,"y":134,"d":"EL289","i":"NX09:5","t":"LEFT","iRe":1},
{"x":3456,"y":158,"d":"EL290","i":"$_EL290_M","t":"NONE"},
{"x":3464,"y":158,"d":"EL290","i":"$_EL290_P","t":"RIGHT","r":["NX1E:5","NX1E:6"],"iSu":1,"f":["$_EL290_P"]},
{"x":3528,"y":158,"d":"EL292","i":"$_EL292","t":"RIGHT","iRe":1},
{"x":3584,"y":134,"d":"EL294","i":"$_EL294_M","t":"NONE"},
{"x":3592,"y":134,"d":"EL294","i":"$_EL294_P","t":"RIGHT","r":["NX1E:7","NX1E:8"],"iSu":1,"f":["$_EL294_P"]},
{"x":3584,"y":334,"d":"EL296","i":"$_EL296_M","t":"NONE"},
{"x":3592,"y":334,"d":"EL296","i":"$_EL296_S","t":"RIGHT","r":["NX1F:1","NX1F:2","NX1F:3","NX1F:4"],"iSu":1,"f":["$_EL296_P"]},
{"x":3768,"y":366,"d":"EL298","i":"$_EL298_M","t":"NONE"},
{"x":3776,"y":366,"d":"EL298","i":"$_EL298_S","t":"RIGHT","r":["NX20:1","NX20:2","NX20:3","NX20:4","NX20:5","NX20:6","NX20:8","NX21:1","NX21:2","NX21:4","NX21:5","NX21:7","NX21:8","NX22:2","NX22:3","NX22:4","NX22:5","NX22:6"],"iSu":1,"f":["$_EL298_P"]},
{"x":3870,"y":334,"d":"EL300","i":"$_EL300_M","t":"NONE"},
{"x":3878,"y":334,"d":"EL300","i":"$_EL300_S","t":"RIGHT","r":["NX23:1","NX23:2","NX23:3","NX23:4","NX23:5","NX23:6","NX23:7","NX23:8","NX24:1","NX24:2","NX24:3","NX24:4","NX24:6","NX24:7","NX24:8","NX25:1","NX25:2","NX25:4","NX25:5","NX25:6","NX25:8","NX26:1","NX26:2","NX26:4","NX26:5","NX26:6","NX26:7","NX26:8","NX27:1","NX27:2"],"iSu":1,"f":["$_EL300_P"]},
{"x":214,"y":278,"d":"EL318","i":"NX0A:4","t":"RIGHT"},
{"x":360,"y":302,"d":"EL320","i":"NX0A:5","t":"RIGHT","r":["NX27:3"]},
{"x":360,"y":334,"d":"EL322","i":"NX0A:6","t":"RIGHT","r":["NX27:4"]},
{"x":480,"y":334,"d":"EL324","i":"$_EL324_M","t":"NONE"},
{"x":488,"y":334,"d":"EL324","i":"$_EL324_P","t":"RIGHT","r":["NX27:5","NX27:6","NX27:7","NX27:8"],"iSu":1,"f":["$_EL324_P"]},
{"x":342,"y":334,"d":"EL325","i":"$_EL325_M","t":"NONE"},
{"x":334,"y":334,"d":"EL325","i":"$_EL325_P","t":"LEFT","r":["NX28:1","NX28:2"],"iSu":1,"f":["$_EL325_P"]},
{"x":550,"y":334,"d":"EL326","i":"NX0B:1","t":"RIGHT","r":["NX28:3"]},
{"x":616,"y":334,"d":"EL326BR","i":"NX0B:1","t":"RIGHT","iBa":1},
{"x":342,"y":278,"d":"EL327","i":"$_EL327_M","t":"NONE"},
{"x":334,"y":278,"d":"EL327","i":"$_EL327_P","t":"LEFT","r":["NX28:4","NX28:5"],"iSu":1,"f":["$_EL327_P"]},
{"x":492,"y":278,"d":"EL329","i":"NX0B:3","t":"LEFT"},
{"x":680,"y":334,"d":"EL330","i":"NX0B:4","t":"RIGHT"},
{"x":744,"y":334,"d":"EL332","i":"NX0B:5","t":"RIGHT"},
{"x":606,"y":278,"d":"EL333","i":"NX0B:6","t":"LEFT"},
{"x":808,"y":334,"d":"EL334","i":"NX0B:7","t":"RIGHT"},
{"x":668,"y":278,"d":"EL335","i":"NX0B:8","t":"LEFT"},
{"x":732,"y":278,"d":"EL337","i":"NX0C:1","t":"LEFT"},
{"x":968,"y":246,"d":"EL336","t":"RIGHT"},
{"x":968,"y":366,"d":"EL338","i":"NX0C:2","t":"RIGHT","r":["NX28:6"]},
{"x":796,"y":278,"d":"EL339","i":"NX0C:3","t":"LEFT","r":["NX28:7"]},
{"x":3148,"y":406,"d":"EL350","i":"$_EL350_M","t":"NONE"},
{"x":3140,"y":406,"d":"EL350","i":"$_EL350_P","t":"LEFT","r":["NX22:7","NX22:8"],"iSu":1,"f":["$_EL350_P"]},
{"x":3088,"y":462,"d":"EL351","i":"NX0C:5","t":"RIGHT"},
{"x":3076,"y":406,"d":"EL352","i":"NX0C:6","t":"LEFT"},
{"x":3024,"y":462,"d":"EL353","i":"NX0C:7","t":"RIGHT"},
{"x":2964,"y":406,"d":"EL354","i":"NX0C:8","t":"LEFT"},
{"x":2932,"y":406,"d":"EL354BR","i":"NX0C:8","t":"LEFT","iBa":1},
{"x":2216,"y":278,"d":"EL3000 LOS","t":"RIGHT","iSh":1},
{"x":2268,"y":334,"d":"EL3001","t":"LEFT","iSh":1,"iAu":1},
{"x":2952,"y":278,"d":"EL3002","t":"RIGHT","iSh":1,"iAu":1},
{"x":3004,"y":334,"d":"EL3003 LOS","t":"LEFT","iSh":1},
{"x":3320,"y":278,"d":"EL3004 LOS","t":"RIGHT","iSh":1},
{"x":3348,"y":310,"d":"EL3005","t":"LEFT","r":["NX2C:8","NX2D:1","NX2D:3","NX2D:5","NX2D:7","NX2D:8","NX2E:2","NX2E:3","NX2E:5"],"iSh":1,"iAu":1},
{"x":3480,"y":642,"d":"EL3006","t":"RIGHT","iSh":1,"iAu":1},
{"x":3452,"y":590,"d":"EL3007","t":"LEFT","iSh":1,"iAu":1},
{"x":3624,"y":642,"d":"EL3008","t":"RIGHT","iSh":1,"iAu":1},
{"x":3452,"y":618,"d":"EL3009","t":"LEFT","iSh":1,"iAu":1},
{"x":3452,"y":646,"d":"EL3011","t":"LEFT","iSh":1,"iAu":1},
{"x":3452,"y":674,"d":"EL3013","t":"LEFT","iSh":1,"iAu":1},
{"x":3644,"y":342,"d":"EL3015","t":"LEFT","iSh":1,"iAu":1},
{"x":3660,"y":370,"d":"EL3017","t":"LEFT","iSh":1,"iAu":1},
{"x":3662,"y":396,"d":"EL3019","t":"LEFT","iSh":1,"iAu":1},
{"x":3662,"y":420,"d":"EL3021","t":"LEFT","iSh":1,"iAu":1},
{"x":3662,"y":444,"d":"EL3023","t":"LEFT","iSh":1,"iAu":1},
{"x":3646,"y":468,"d":"EL3025","t":"LEFT","iSh":1,"iAu":1},
{"x":3646,"y":492,"d":"EL3027","t":"LEFT","iSh":1,"iAu":1},
{"x":3646,"y":516,"d":"EL3029","t":"LEFT","iSh":1,"iAu":1},
{"x":3646,"y":540,"d":"EL3031","t":"LEFT","iSh":1,"iAu":1},
{"x":3646,"y":564,"d":"EL3033","t":"LEFT","iSh":1,"iAu":1},
{"x":3646,"y":588,"d":"EL3035","t":"LEFT","iSh":1,"iAu":1},
{"x":3612,"y":642,"d":"EL3037","t":"LEFT","iSh":1,"iAu":1},
{"x":440,"y":302,"d":"EL3040","t":"RIGHT","iSh":1,"iAu":1},
{"x":3268,"y":342,"d":"EL3051","t":"LEFT","iSh":1,"iAu":1},
{"x":3268,"y":370,"d":"EL3053","t":"LEFT","iSh":1,"iAu":1},
{"x":3252,"y":398,"d":"EL3055","t":"LEFT","iSh":1,"iAu":1},
{"x":3252,"y":426,"d":"EL3057","t":"LEFT","iSh":1,"iAu":1},
{"x":3252,"y":454,"d":"EL3059","t":"LEFT","iSh":1,"iAu":1},
{"x":3252,"y":482,"d":"EL3061","t":"LEFT","iSh":1,"iAu":1},
{"x":3252,"y":510,"d":"EL3063","t":"LEFT","iSh":1,"iAu":1},
{"x":3252,"y":538,"d":"EL3065","t":"LEFT","iSh":1,"iAu":1},
{"x":3252,"y":566,"d":"EL3067","t":"LEFT","iSh":1,"iAu":1},
{"x":3252,"y":594,"d":"EL3069","t":"LEFT","iSh":1,"iAu":1},
{"x":280,"y":174,"d":"K375","i":"Y91A:5","t":"RIGHT","r":["Y90F:3"]},
{"x":152,"y":270,"d":"NL1234","i":"U310:1","t":"RIGHT","r":["U303:6","U303:7"]},
{"x":334,"y":270,"d":"NL1239","t":"LEFT"},
{"x":214,"y":270,"d":"NL1242","i":"U310:6","t":"RIGHT","r":["U304:3"]},
{"x":304,"y":270,"d":"NL1242BR","i":"$_NL1242_BR","t":"RIGHT","iBa":1},
{"x":396,"y":150,"d":"NL1243","i":"U310:7","t":"LEFT","r":["U304:4"]},
{"x":214,"y":214,"d":"NL1244","t":"RIGHT"},
{"x":334,"y":214,"d":"NL1245","i":"U311:1","t":"LEFT","r":["U304:5"]},
{"x":360,"y":270,"d":"NL1246","i":"U311:2","t":"RIGHT","r":["U304:6"]},
{"x":606,"y":214,"d":"NL1247","i":"U311:3","t":"LEFT"},
{"x":360,"y":238,"d":"NL1248","t":"RIGHT","iRe":1},
{"x":606,"y":270,"d":"NL1249","t":"LEFT","iRe":1},
{"x":488,"y":270,"d":"NL1250","i":"U311:4","t":"RIGHT","r":["U304:7"]},
{"x":732,"y":214,"d":"NL1251","i":"U311:8","t":"LEFT"},
{"x":700,"y":214,"d":"NL1251BR","i":"U311:8","t":"LEFT","iBa":1},
{"x":732,"y":246,"d":"NL1253","t":"LEFT"},
{"x":550,"y":270,"d":"NL1254","i":"U311:5","t":"RIGHT","r":["U304:8","U305:1","U305:2"]},
{"x":616,"y":276,"d":"NL1254BR1","i":"$_NL1254_1_BR","t":"RIGHT","iBa":1},
{"x":622,"y":270,"d":"NL1254BR2","i":"$_NL1254_2_BR","t":"RIGHT","iBa":1},
{"x":680,"y":270,"d":"NL1256","i":"U312:2","t":"RIGHT"},
{"x":744,"y":270,"d":"NL1258","i":"U312:4","t":"RIGHT"},
{"x":204,"y":214,"d":"NL1311","i":"U311:6","t":"LEFT","r":["U305:3"]},
{"x":204,"y":246,"d":"NL1313","t":"LEFT","iRe":1},
{"x":492,"y":214,"d":"NL1315","i":"U311:7","t":"LEFT","r":["U305:4","U305:5"]},
{"x":412,"y":214,"d":"NL1315BR","i":"U311:7","t":"LEFT","iBa":1},
{"x":668,"y":214,"d":"NL1317","i":"U315:3","t":"LEFT"},
{"x":668,"y":246,"d":"NL1319","t":"LEFT","iRe":1},
{"x":2960,"y":462,"d":"TL615","i":"X143:8","t":"RIGHT","r":["X152:6"]},
{"x":2992,"y":462,"d":"TL615BR","i":"X143:8","t":"RIGHT","iBa":1},
{"x":3582,"y":222,"d":"TL2444","i":"$_TL2444_M","t":"NONE"},
{"x":3590,"y":222,"d":"TL2444","i":"$_TL2444_P","t":"RIGHT","r":["X30E:8","X31B:5"],"iSu":1,"f":["$_TL2444_P"]},
{"x":3716,"y":198,"d":"TL2451","i":"$_TL2451_M","t":"NONE"},
{"x":3708,"y":198,"d":"TL2451","i":"$_TL2451_P","t":"LEFT","r":["X30F:8","X31C:5"],"iSu":1,"f":["$_TL2451_P"]},
{"x":3584,"y":254,"d":"TL2546","i":"$_TL2546_M","t":"NONE"},
{"x":3592,"y":254,"d":"TL2546","i":"$_TL2546_P","t":"RIGHT","r":["X312:6","X312:7","X31F:3","X31F:4"],"iSu":1,"f":["$_TL2546_P"]},
{"x":3718,"y":166,"d":"TL2559","i":"$_TL2559_M","t":"NONE"},
{"x":3710,"y":166,"d":"TL2559","i":"$_TL2559_P","t":"LEFT","r":["X314:2","X320:4"],"iSu":1,"f":["$_TL2559_P"]},
{"x":3870,"y":494,"d":"TL4018","i":"$_TL4018_M","t":"NONE"},
{"x":3878,"y":494,"d":"TL4018","i":"$_TL4018_S","t":"RIGHT","r":["X10E:6","X10E:7","X10E:8","X10F:1","X10F:2","X10F:3","X10F:4"],"iSu":1,"f":["$_TL4018_P"]},
{"x":4006,"y":374,"d":"TL4027","i":"$_TL4027_M","t":"NONE"},
{"x":3998,"y":374,"d":"TL4027","i":"$_TL4027_P","t":"LEFT","r":["X110:8","X111:1","X111:2","X111:3"],"iSu":1,"f":["$_TL4027_P"]},
{"x":3872,"y":462,"d":"TL4446","i":"$_TL4446_M","t":"NONE"},
{"x":3880,"y":462,"d":"TL4446","i":"$_TL4446_S","t":"RIGHT","r":["X122:2","X122:3","X122:4","X122:5","X122:6","X122:7","X122:8"],"iSu":1,"f":["$_TL4446_P"]},
{"x":4004,"y":406,"d":"TL4455","i":"$_TL4455_M","t":"NONE"},
{"x":3996,"y":406,"d":"TL4455","i":"$_TL4455_P","t":"LEFT","r":["X124:6","X124:7"],"iSu":1,"f":["$_TL4455_P"]},
{"x":4004,"y":310,"d":"TL4629","i":"$_TL4629_M","t":"NONE"},
{"x":3996,"y":310,"d":"TL4629","i":"$_TL4629_P","t":"LEFT","r":["X127:2","X127:3"],"iSu":1,"f":["$_TL4629_P"]},
{"x":3880,"y":398,"d":"TL5130","i":"X133:4","t":"RIGHT","r":["X128:3","X128:4","X128:5"],"iSh":1},
{"x":3878,"y":430,"d":"TL5132","i":"X133:5","t":"RIGHT","r":["X128:6","X128:7","X128:8"],"iSh":1},
{"x":3998,"y":494,"d":"TL5139 LOS","i":"X133:7","t":"LEFT","iSh":1},
{"x":3998,"y":438,"d":"TL5141 LOS","i":"X134:1","t":"LEFT","iSh":1}
],
"points":[
{"x":1082,"y":314,"d":"EL100 Nrm","i":["NX0D:1","NX0D:3","NX0D:5","NX0E:2","NX0E:3","NX0E:4","NX0E:8","NX0F:1","NX0F:4","NX0F:6"],"1":"NHzLfUR"},
{"x":1082,"y":314,"d":"EL100 Rev","i":["NX0E:6","NX0E:7","NX0F:2","NX0F:3"],"1":"RHzLfUR"},
{"x":1098,"y":298,"d":"EL100/103X Rev","i":["NX0E:6","NX0E:7","NX0F:2","NX0F:3"],"1":"XOInc"},
{"x":1082,"y":282,"d":"EL101 Nrm","i":["NX0D:3","NX0D:4","NX0D:8","NX0E:2","NX0E:6","NX0E:8","NX0F:2","NX0F:4","NX0F:5","NX0F:8"],"1":"NHzLfLR"},
{"x":1082,"y":282,"d":"EL101 Rev","i":["NX0D:5","NX0D:6","NX0E:4","NX0E:5"],"1":"RHzLfLR"},
{"x":1098,"y":298,"d":"EL101/102X Rev","i":["NX0D:5","NX0D:6","NX0E:4","NX0E:5"],"1":"XODcl"},
{"x":1114,"y":314,"d":"EL102 Nrm","i":["NX0D:3","NX0D:8","NX0E:2","NX0E:3","NX0E:6","NX0E:8","NX0F:1","NX0F:2","NX0F:4","NX0F:8"],"1":"NHzRtUL"},
{"x":1114,"y":314,"d":"EL102 Rev","i":["NX0D:5","NX0D:6","NX0E:4","NX0E:5"],"1":"RHzRtUL"},
{"x":1114,"y":282,"d":"EL103 Nrm","i":["NX0D:1","NX0D:3","NX0D:4","NX0D:5","NX0E:2","NX0E:4","NX0E:8","NX0F:4","NX0F:5","NX0F:6"],"1":"NHzRtLL"},
{"x":1114,"y":282,"d":"EL103 Rev","i":["NX0E:6","NX0E:7","NX0F:2","NX0F:3"],"1":"RHzRtLL"},
{"x":1130,"y":314,"d":"EL104 Nrm","i":["NX0D:5","NX0D:6","NX0E:2","NX0E:3","NX0E:4","NX0E:5","NX0E:7","NX0E:8","NX0F:1"],"1":"NHzRtLL"},
{"x":1130,"y":314,"d":"EL104 Rev","i":["NX0D:8","NX0E:1","NX0F:8","NX10:1"],"1":"RHzRtLL"},
{"x":1130,"y":282,"d":"EL105 Nrm","i":["NX0D:3","NX0D:4","NX0E:6","NX0F:2","NX0F:3","NX0F:4","NX0F:5"],"1":"NHzRtUL"},
{"x":1130,"y":282,"d":"EL105 Rev","i":["NX0D:1","NX0D:2","NX0F:6","NX0F:7"],"1":"RHzRtUL"},
{"x":1258,"y":314,"d":"EL106 Nrm","i":["NX10:2","NX10:3","NX10:4","NX10:6"],"1":"NHzLfUR"},
{"x":1258,"y":314,"d":"EL106 Rev","i":["NX10:8","NX11:1"],"1":"RHzLfUR"},
{"x":1274,"y":298,"d":"EL106/109X Rev","i":["NX10:8","NX11:1"],"1":"XOInc"},
{"x":1258,"y":282,"d":"EL107 Nrm","i":["NX10:2","NX10:6","NX10:7","NX10:8"],"1":"NHzLfLR"},
{"x":1258,"y":282,"d":"EL107 Rev","i":["NX10:4","NX10:5"],"1":"RHzLfLR"},
{"x":1274,"y":298,"d":"EL107/108X Rev","i":["NX10:4","NX10:5"],"1":"XODcl"},
{"x":1290,"y":314,"d":"EL108 Nrm","i":["NX10:2","NX10:3","NX10:6","NX10:8"],"1":"NHzRtUL"},
{"x":1290,"y":314,"d":"EL108 Rev","i":["NX10:4","NX10:5"],"1":"RHzRtUL"},
{"x":1290,"y":282,"d":"EL109 Nrm","i":["NX10:2","NX10:4","NX10:6","NX10:7"],"1":"NHzRtLL"},
{"x":1290,"y":282,"d":"EL109 Rev","i":["NX10:8","NX11:1"],"1":"RHzRtLL"},
{"x":2266,"y":282,"d":"EL115 Nrm","i":["NX11:2","NX11:6","NX11:8","NX12:1"],"1":"NHzLfLR"},
{"x":2266,"y":282,"d":"EL115 Rev","i":["NX11:4","NX12:2","NX12:3"],"1":"RHzLfLR"},
{"x":2282,"y":298,"d":"EL115/118X Rev","i":["NX11:4","NX12:2","NX12:3"],"1":"XODcl"},
{"x":2266,"y":314,"d":"EL116 Nrm","i":["NX11:2","NX11:3","NX11:4","NX11:8","NX12:2"],"1":"NHzLfUR"},
{"x":2266,"y":314,"d":"EL116 Rev","i":["NX11:6","NX11:7"],"1":"RHzLfUR"},
{"x":2282,"y":298,"d":"EL116/117X Rev","i":["NX11:6","NX11:7"],"1":"XOInc"},
{"x":2298,"y":282,"d":"EL117 Nrm","i":["NX11:2","NX11:4","NX11:8","NX12:1","NX12:2"],"1":"NHzRtLL"},
{"x":2298,"y":282,"d":"EL117 Rev","i":["NX11:6","NX11:7"],"1":"RHzRtLL"},
{"x":2298,"y":314,"d":"EL118 Nrm","i":["NX11:2","NX11:3","NX11:6","NX11:8"],"1":"NHzRtUL"},
{"x":2298,"y":314,"d":"EL118 Rev","i":["NX11:4","NX12:2","NX12:3"],"1":"RHzRtUL"},
{"x":2906,"y":282,"d":"EL121 Nrm","i":["NX12:8","NX13:1","NX13:3","NX13:7"],"1":"NHzLfLR"},
{"x":2906,"y":282,"d":"EL121 Rev","i":["NX13:2","NX13:5","NX13:6"],"1":"RHzLfLR"},
{"x":2922,"y":298,"d":"EL121/124X Rev","i":["NX13:2","NX13:5","NX13:6"],"1":"XODcl"},
{"x":2906,"y":314,"d":"EL122 Nrm","i":["NX12:8","NX13:2","NX13:3","NX13:4","NX13:5"],"1":"NHzLfUR"},
{"x":2906,"y":314,"d":"EL122 Rev","i":["NX13:7","NX13:8"],"1":"RHzLfUR"},
{"x":2922,"y":298,"d":"EL122/123X Rev","i":["NX13:7","NX13:8"],"1":"XOInc"},
{"x":2938,"y":282,"d":"EL123 Nrm","i":["NX12:8","NX13:1","NX13:2","NX13:3","NX13:5"],"1":"NHzRtLL"},
{"x":2938,"y":282,"d":"EL123 Rev","i":["NX13:7","NX13:8"],"1":"RHzRtLL"},
{"x":2938,"y":314,"d":"EL124 Nrm","i":["NX12:8","NX13:3","NX13:4","NX13:7"],"1":"NHzRtUL"},
{"x":2938,"y":314,"d":"EL124 Rev","i":["NX13:2","NX13:5","NX13:6"],"1":"RHzRtUL"},
{"x":3482,"y":314,"d":"EL126 Nrm","i":["NX1D:3","NX1D:4","NX1E:1","NX1E:2","NX1F:1","NX1F:2","NX2A:5","NX2A:6","NX2B:1","NX2B:2","NX2C:8","NX2D:1","NX2D:3"],"1":"NHzLfDn"},
{"x":3482,"y":314,"d":"EL126 Rev","i":["NX1B:3","NX1B:4","NX1C:1","NX1C:2","NX1C:5","NX1C:6","NX2B:5","NX2B:8","NX2C:3","NX2D:5","NX2D:7","NX2D:8","NX2E:2","NX2E:3","NX2E:5"],"1":"RHzLfDn"},
{"x":3434,"y":314,"d":"EL128 Nrm","i":["NX18:6","NX18:8","NX19:2","NX19:5","NX19:8","NX1A:1","NX1A:7","NX1B:3","NX1B:4","NX1C:1","NX1C:2","NX1C:5","NX1C:6","NX1D:3","NX1D:4","NX1D:5","NX1E:1","NX1E:2","NX1E:3","NX1F:1","NX1F:2","NX1F:3","NX2A:5","NX2A:6","NX2B:1","NX2B:2","NX2B:5","NX2B:8","NX2C:3","NX2C:8","NX2D:1","NX2D:3","NX2D:5","NX2D:7","NX2D:8","NX2E:2","NX2E:3","NX2E:5"],"1":"NHzLfUp"},
{"x":3434,"y":314,"d":"EL128 Rev","i":["NX1E:5","NX1E:6"],"1":"RHzLfUp"},
{"x":3434,"y":282,"d":"EL128/9X Nrm","i":["NX18:6","NX18:7","NX18:8","NX19:1","NX19:2","NX19:4","NX19:5","NX19:7","NX1A:7","NX1A:8","NX1D:5","NX1D:6","NX1E:3","NX1E:4","NX1F:3","NX1F:4"],"1":"XOHz"},
{"x":3434,"y":282,"d":"EL128/9X Rev","i":["NX1E:5","NX1E:6"],"1":"XOVt"},
{"x":3418,"y":282,"d":"EL129 Nrm","i":["NX18:4","NX18:5","NX1A:5","NX1A:6","NX1E:5","NX1E:6"],"1":"RHzLfUp"},
{"x":3418,"y":282,"d":"EL129 Rev","i":["NX18:6","NX18:7","NX18:8","NX19:1","NX19:2","NX19:4","NX19:5","NX19:7","NX1A:7","NX1A:8","NX1D:5","NX1D:6","NX1E:3","NX1E:4","NX1F:3","NX1F:4"],"1":"NHzLfUp"},
{"x":3450,"y":314,"d":"EL130 Nrm","i":["NX19:8","NX1A:1"],"1":"RHzLfDn"},
{"x":3450,"y":314,"d":"EL130 Rev","i":["NX1B:3","NX1B:4","NX1C:1","NX1C:2","NX1C:5","NX1C:6","NX1D:3","NX1D:4","NX1E:1","NX1E:2","NX1F:1","NX1F:2","NX2A:5","NX2A:6","NX2B:1","NX2B:2","NX2B:5","NX2B:8","NX2C:3","NX2C:8","NX2D:1","NX2D:3","NX2D:5","NX2D:7","NX2D:8","NX2E:2","NX2E:3","NX2E:5"],"1":"NHzLfDn"},
{"x":3498,"y":282,"d":"EL131 Nrm","i":["NX18:6","NX18:7","NX1A:7","NX1A:8","NX1D:3","NX1E:1","NX1F:1","NX2A:5","NX2A:6","NX2B:1","NX2B:2","NX2C:8","NX2D:1","NX2D:3"],"1":"NHzLfDn"},
{"x":3498,"y":282,"d":"EL131 Rev","i":["NX18:8","NX19:1","NX19:2","NX19:4","NX19:5","NX19:7","NX1D:5","NX1D:6","NX1E:3","NX1E:4","NX1F:3","NX1F:4"],"1":"RHzLfDn"},
{"x":3498,"y":314,"d":"EL132A Nrm","i":["NX18:8","NX19:1","NX1F:1","NX1F:2","NX1F:3","NX1F:4","NX2A:5","NX2A:6"],"1":"RUpRt"},
{"x":3498,"y":314,"d":"EL132A Rev","i":["NX19:2","NX19:4","NX19:5","NX19:7","NX1D:3","NX1D:4","NX1D:5","NX1D:6","NX1E:1","NX1E:2","NX1E:3","NX1E:4","NX2B:1","NX2B:2","NX2C:8","NX2D:1","NX2D:3"],"1":"NVtRtUp"},
{"x":3498,"y":314,"d":"EL132B Nrm","i":["NX18:8","NX19:1","NX1F:1","NX1F:2","NX1F:3","NX1F:4","NX2A:5","NX2A:6"],"1":"NHzLfDn"},
{"x":3498,"y":314,"d":"EL132B Rev","i":["NX19:2","NX19:4","NX19:5","NX19:7","NX1D:3","NX1D:4","NX1D:5","NX1D:6","NX1E:1","NX1E:2","NX1E:3","NX1E:4","NX2B:1","NX2B:2","NX2C:8","NX2D:1","NX2D:3"],"1":"RLfDn"},
{"x":3498,"y":314,"d":"EL132/134 Dot","i":["NX18:8","NX19:1","NX1D:3","NX1D:4","NX1E:1","NX1E:2","NX1F:3","NX1F:4","NX2B:1","NX2B:2","NX2C:8","NX2D:1","NX2D:3"],"1":"Dot"},
{"x":3498,"y":314,"d":"EL134A Nrm","i":["NX18:6","NX18:7","NX1A:7","NX1A:8","NX1D:3","NX1D:4","NX1E:1","NX1E:2","NX1F:1","NX1F:2","NX2A:5","NX2A:6","NX2B:1","NX2B:2","NX2C:8","NX2D:1","NX2D:3"],"1":"NHzRtUp"},
{"x":3498,"y":314,"d":"EL134A Rev","i":["NX18:8","NX19:1","NX19:2","NX19:4","NX19:5","NX19:7","NX1D:5","NX1D:6","NX1E:3","NX1E:4","NX1F:3","NX1F:4"],"1":"RRtUp"},
{"x":3498,"y":314,"d":"EL134B Nrm","i":["NX18:6","NX18:7","NX1A:7","NX1A:8","NX1D:3","NX1D:4","NX1E:1","NX1E:2","NX1F:1","NX1F:2","NX2A:5","NX2A:6","NX2B:1","NX2B:2","NX2C:8","NX2D:1","NX2D:3"],"1":"RDnLf"},
{"x":3498,"y":314,"d":"EL134B Rev","i":["NX18:8","NX19:1","NX19:2","NX19:4","NX19:5","NX19:7","NX1D:5","NX1D:6","NX1E:3","NX1E:4","NX1F:3","NX1F:4"],"1":"NVtLfDn"},
{"x":3642,"y":314,"d":"EL136 Nrm","i":["NX1B:5","NX1B:6","NX22:4","NX26:7","NX26:8","NX27:1","NX27:2"],"1":"NHzLfDn"},
{"x":3642,"y":314,"d":"EL136 Rev","i":["NX1B:7","NX1B:8","NX22:5","NX22:6"],"1":"RHzLfDn"},
{"x":3738,"y":314,"d":"EL137 Nrm","i":["NX1C:3","NX1C:4","NX27:1","NX27:2"],"1":"NHzRtUL"},
{"x":3738,"y":314,"d":"EL137 Rev","i":["NX1A:3","NX1A:4"],"1":"RHzRtUL"},
{"x":3762,"y":314,"d":"EL139 Nrm","i":["NX1A:3","NX1A:4","NX1C:3","NX1C:4","NX1D:2","NX20:1","NX20:2","NX20:3","NX20:4","NX20:5","NX20:6","NX20:8","NX21:1","NX21:2","NX21:4","NX21:5","NX21:7","NX21:8","NX22:2","NX22:3","NX22:4","NX22:5","NX22:6","NX27:1","NX27:2"],"1":"NHzRtDn"},
{"x":3762,"y":314,"d":"EL139 Rev","i":["NX1C:7","NX1D:1","NX23:1","NX23:2","NX23:3","NX23:4","NX23:5","NX23:6","NX23:7","NX23:8","NX24:1","NX24:2","NX24:3","NX24:4","NX24:6","NX24:7","NX24:8","NX25:1","NX25:2","NX25:4","NX25:5","NX25:6","NX25:8","NX26:1","NX26:2","NX26:4","NX26:5","NX26:6","NX26:7","NX26:8"],"1":"RHzRtDn"},
{"x":410,"y":314,"d":"EL141 Nrm","i":["NX27:5","NX27:6","NX27:7","NX27:8","NX28:4","NX28:5"],"1":"NHzLfUp"},
{"x":410,"y":314,"d":"EL141 Rev","i":["NX28:1","NX28:2"],"1":"RHzLfUp"},
{"x":410,"y":282,"d":"EL142 Nrm","i":["NX27:5","NX27:6","NX27:7","NX27:8","NX28:4","NX28:5"],"1":"NHzRtDn"},
{"x":410,"y":282,"d":"EL142 Rev","i":["NX28:1","NX28:2"],"1":"RHzRtDn"},
{"x":426,"y":282,"d":"EL143 Nrm","i":["NX27:5","NX27:6","NX28:1","NX28:2","NX28:4","NX28:5"],"1":"NHzLfDn"},
{"x":426,"y":282,"d":"EL143 Rev","i":["NX27:7","NX27:8"],"1":"RHzLfDn"},
{"x":426,"y":314,"d":"EL144 Nrm","i":["NX27:5","NX27:6","NX28:1","NX28:2","NX28:4","NX28:5"],"1":"NHzRtUp"},
{"x":426,"y":314,"d":"EL144 Rev","i":["NX27:7","NX27:8"],"1":"RHzRtUp"},
{"x":3170,"y":282,"d":"EL147 Nrm","i":["NX14:3","NX14:4"],"1":"NHzLfDn"},
{"x":3170,"y":282,"d":"EL147 Rev","i":["NX14:5","NX14:6"],"1":"RHzLfDn"},
{"x":3146,"y":314,"d":"EL148 Nrm","i":["NX14:7","NX14:8"],"1":"NHzLfDn"},
{"x":3146,"y":314,"d":"EL148 Rev","i":["NX22:7","NX22:8"],"1":"RHzLfDn"},
{"x":3266,"y":570,"d":"EL159 Nrm","i":["NX15:2","NX15:3"],"1":"NVtLfUp"},
{"x":3266,"y":570,"d":"EL159 Rev","i":["NX15:4","NX15:5"],"1":"RVtLfUp"},
{"x":3266,"y":542,"d":"EL160 Nrm","i":["NX15:2","NX15:3","NX15:4","NX15:5"],"1":"NVtLfUp"},
{"x":3266,"y":542,"d":"EL160 Rev","i":["NX15:6","NX15:7"],"1":"RVtLfUp"},
{"x":3250,"y":486,"d":"EL161 Nrm","i":["NX15:8","NX16:1"],"1":"NVtLfUp"},
{"x":3250,"y":486,"d":"EL161 Rev","i":["NX16:2","NX16:3"],"1":"RVtLfUp"},
{"x":3250,"y":458,"d":"EL162 Nrm","i":["NX16:4","NX16:5"],"1":"NHzRtDn"},
{"x":3250,"y":458,"d":"EL162 Rev","i":["NX15:8","NX16:1","NX16:2","NX16:3"],"1":"RHzRtDn"},
{"x":3266,"y":458,"d":"EL163 Nrm","i":["NX15:8","NX16:1","NX16:2","NX16:3","NX16:4","NX16:5"],"1":"NHzRtDn"},
{"x":3266,"y":458,"d":"EL163 Rev","i":["NX15:2","NX15:3","NX15:4","NX15:5","NX15:6","NX15:7"],"1":"RHzRtDn"},
{"x":3250,"y":402,"d":"EL164 Nrm","i":["NX16:8","NX17:1"],"1":"NHzRtDn"},
{"x":3250,"y":402,"d":"EL164 Rev","i":["NX16:6","NX16:7"],"1":"RHzRtDn"},
{"x":3266,"y":374,"d":"EL165 Nrm","i":["NX16:6","NX16:7","NX16:8","NX17:1"],"1":"NVtLfUp"},
{"x":3266,"y":374,"d":"EL165 Rev","i":["NX17:2","NX17:3"],"1":"RVtLfUp"},
{"x":3266,"y":346,"d":"EL166 Nrm","i":["NX17:4","NX17:5"],"1":"NHzRtDn"},
{"x":3266,"y":346,"d":"EL166 Rev","i":["NX16:6","NX16:7","NX16:8","NX17:1","NX17:2","NX17:3"],"1":"RHzRtDn"},
{"x":3282,"y":346,"d":"EL167 Nrm","i":["NX16:6","NX16:7","NX16:8","NX17:1","NX17:2","NX17:3","NX17:4","NX17:5"],"1":"NHzRtDn"},
{"x":3282,"y":346,"d":"EL167 Rev","i":["NX15:2","NX15:3","NX15:4","NX15:5","NX15:6","NX15:7","NX15:8","NX16:1","NX16:2","NX16:3","NX16:4","NX16:5"],"1":"RHzRtDn"},
{"x":3762,"y":346,"d":"EL168 Nrm","i":["NX1A:3","NX1C:3","NX1D:2","NX20:1","NX20:2","NX20:3","NX20:4","NX20:5","NX20:6","NX20:8","NX21:1","NX21:2","NX21:4","NX21:5","NX21:7","NX21:8","NX22:2","NX22:3","NX22:4","NX22:5","NX22:6","NX27:1"],"1":"NHzLfUp"},
{"x":3762,"y":346,"d":"EL168 Rev","i":["NX1C:7","NX1D:1","NX23:1","NX23:2","NX23:3","NX23:4","NX23:5","NX23:6","NX23:7","NX23:8","NX24:1","NX24:2","NX24:3","NX24:4","NX24:6","NX24:7","NX24:8","NX25:1","NX25:2","NX25:4","NX25:5","NX25:6","NX25:8","NX26:1","NX26:2","NX26:4","NX26:5","NX26:6","NX26:7","NX26:8"],"1":"RHzLfUp"},
{"x":3354,"y":346,"d":"EL182 Nrm","i":["NX17:6","NX17:7","NX2C:8","NX2D:1","NX2D:3","NX2D:5","NX2D:7","NX2D:8","NX2E:2","NX2E:3","NX2E:5"],"1":"NHzLfUp"},
{"x":3354,"y":346,"d":"EL182 Rev","i":["NX15:2","NX15:3","NX15:4","NX15:5","NX15:6","NX15:7","NX15:8","NX16:1","NX16:2","NX16:3","NX16:4","NX16:5","NX16:6","NX16:7","NX16:8","NX17:1","NX17:2","NX17:3","NX17:4","NX17:5","NX1A:5","NX1A:6","NX1A:7","NX1A:8","NX2A:5","NX2A:6","NX2B:1","NX2B:2","NX2B:5","NX2B:8","NX2C:3"],"1":"RHzLfUp"},
{"x":3354,"y":314,"d":"EL183 Nrm","i":["NX17:6","NX17:7","NX2C:8","NX2D:1","NX2D:3","NX2D:5","NX2D:7","NX2D:8","NX2E:2","NX2E:3","NX2E:5"],"1":"NHzRtDn"},
{"x":3354,"y":314,"d":"EL183 Rev","i":["NX15:2","NX15:3","NX15:4","NX15:5","NX15:6","NX15:7","NX15:8","NX16:1","NX16:2","NX16:3","NX16:4","NX16:5","NX16:6","NX16:7","NX16:8","NX17:1","NX17:2","NX17:3","NX17:4","NX17:5","NX1A:5","NX1A:6","NX1A:7","NX1A:8","NX2A:5","NX2A:6","NX2B:1","NX2B:2","NX2B:5","NX2B:8","NX2C:3"],"1":"RHzRtDn"},
{"x":3370,"y":314,"d":"EL184 Nrm","i":["NX15:2","NX15:3","NX15:4","NX15:5","NX15:6","NX15:7","NX15:8","NX16:1","NX16:2","NX16:3","NX16:4","NX16:5","NX16:6","NX16:7","NX16:8","NX17:1","NX17:2","NX17:3","NX17:4","NX17:5","NX17:6","NX17:7","NX18:4","NX18:5","NX18:6","NX18:7","NX18:8","NX19:1","NX19:2","NX19:4","NX19:5","NX19:7","NX1D:5","NX1E:3","NX1F:3","NX2A:5","NX2A:6","NX2B:1","NX2B:2","NX2B:5","NX2B:8","NX2C:3","NX2C:8","NX2D:1","NX2D:3","NX2D:5","NX2D:7","NX2D:8","NX2E:2","NX2E:3","NX2E:5"],"1":"NHzLfUp"},
{"x":3370,"y":314,"d":"EL184 Rev","i":["NX1A:5","NX1A:6","NX1A:7","NX1A:8"],"1":"RHzLfUp"},
{"x":3370,"y":282,"d":"EL185 Nrm","i":["NX15:2","NX15:3","NX15:4","NX15:5","NX15:6","NX15:7","NX15:8","NX16:1","NX16:2","NX16:3","NX16:4","NX16:5","NX16:6","NX16:7","NX16:8","NX17:1","NX17:2","NX17:3","NX17:4","NX17:5","NX17:6","NX17:7","NX18:4","NX18:5","NX18:6","NX18:7","NX18:8","NX19:1","NX19:2","NX19:4","NX19:5","NX19:7","NX1D:5","NX1D:6","NX1E:3","NX1E:4","NX1F:3","NX1F:4","NX2A:5","NX2A:6","NX2B:1","NX2B:2","NX2B:5","NX2B:8","NX2C:3","NX2C:8","NX2D:1","NX2D:3","NX2D:5","NX2D:7","NX2D:8","NX2E:2","NX2E:3","NX2E:5"],"1":"NHzRtDn"},
{"x":3370,"y":282,"d":"EL185 Rev","i":["NX1A:5","NX1A:6","NX1A:7","NX1A:8"],"1":"RHzRtDn"},
{"x":3514,"y":138,"d":"EL190 Nrm","i":["NX1E:7","NX1E:8"],"1":"NHzRtUp"},
{"x":3514,"y":138,"d":"EL190 Rev","i":["NX1D:7","NX1D:8"],"1":"RHzRtUp"},
{"x":3482,"y":398,"d":"EL200 Nrm","i":["NX1B:3","NX1B:4","NX2C:3","NX2E:3","NX2E:5"],"1":"NVtRtUp"},
{"x":3482,"y":398,"d":"EL200 Rev","i":["NX1C:1","NX1C:2","NX1C:5","NX1C:6","NX2B:5","NX2B:8","NX2D:5","NX2D:7","NX2D:8","NX2E:2"],"1":"RVtRtUp"},
{"x":3498,"y":346,"d":"EL201 Nrm","i":["NX19:5","NX19:7","NX1D:3","NX1D:4","NX1D:5","NX1D:6","NX2B:2","NX2D:1","NX2D:3"],"1":"NVtRtUp"},
{"x":3498,"y":346,"d":"EL201 Rev","i":["NX19:2","NX19:4","NX1E:1","NX1E:2","NX1E:3","NX1E:4","NX2B:1","NX2C:8"],"1":"RVtRtUp"},
{"x":3498,"y":398,"d":"EL202 Nrm","i":["NX1C:5","NX1C:6","NX2B:5","NX2D:5","NX2D:7"],"1":"NHzLfDn"},
{"x":3498,"y":398,"d":"EL202 Rev","i":["NX1C:1","NX1C:2","NX2B:8","NX2D:8","NX2E:2"],"1":"RHzLfDn"},
{"x":3642,"y":346,"d":"EL203 Nrm","i":["NX1B:5","NX22:4","NX26:7","NX26:8","NX27:1"],"1":"NHzRtUp"},
{"x":3642,"y":346,"d":"EL203 Rev","i":["NX1B:7","NX1B:8","NX22:5","NX22:6"],"1":"RHzRtUp"},
{"x":3658,"y":346,"d":"EL204 Nrm","i":["NX1B:7","NX1B:8","NX22:4","NX22:5","NX22:6","NX26:7","NX26:8"],"1":"NHzRtDn"},
{"x":3658,"y":346,"d":"EL204 Rev","i":["NX22:2","NX22:3","NX26:4","NX26:5","NX26:6"],"1":"RHzRtDn"},
{"x":3658,"y":518,"d":"EL205 Nrm","i":["NX20:5","NX24:1","NX24:2"],"1":"NHzRtDn"},
{"x":3658,"y":518,"d":"EL205 Rev","i":["NX20:4","NX23:7","NX23:8"],"1":"RHzRtDn"},
{"x":3674,"y":346,"d":"EL206 Nrm","i":["NX1B:7","NX1B:8","NX22:2","NX22:3","NX22:4","NX22:5","NX22:6","NX26:4","NX26:5","NX26:6","NX26:7","NX26:8"],"1":"NHzRtDn"},
{"x":3674,"y":346,"d":"EL206 Rev","i":["NX21:4","NX21:5","NX21:7","NX21:8","NX25:4","NX25:5","NX25:6","NX25:8","NX26:1","NX26:2"],"1":"RHzRtDn"},
{"x":3674,"y":398,"d":"EL207 Nrm","i":["NX21:4","NX21:5","NX25:4","NX25:5","NX25:6"],"1":"NVtLfUp"},
{"x":3674,"y":398,"d":"EL207 Rev","i":["NX21:7","NX21:8","NX25:8","NX26:1","NX26:2"],"1":"RVtLfUp"},
{"x":3674,"y":446,"d":"EL208 Nrm","i":["NX21:2","NX25:1","NX25:2"],"1":"NHzRtDn"},
{"x":3674,"y":446,"d":"EL208 Rev","i":["NX20:6","NX20:8","NX21:1","NX24:3","NX24:4","NX24:6","NX24:7","NX24:8"],"1":"RHzRtDn"},
{"x":3674,"y":470,"d":"EL209 Nrm","i":["NX20:6","NX24:3","NX24:4"],"1":"NVtLfUp"},
{"x":3674,"y":470,"d":"EL209 Rev","i":["NX20:8","NX21:1","NX24:6","NX24:7","NX24:8"],"1":"RVtLfUp"},
{"x":3690,"y":346,"d":"EL210 Nrm","i":["NX1B:7","NX1B:8","NX21:4","NX21:5","NX21:7","NX21:8","NX22:2","NX22:3","NX22:4","NX22:5","NX22:6","NX25:4","NX25:5","NX25:6","NX25:8","NX26:1","NX26:2","NX26:4","NX26:5","NX26:6","NX26:7","NX26:8"],"1":"NHzRtDn"},
{"x":3690,"y":346,"d":"EL210 Rev","i":["NX20:1","NX20:2","NX20:3","NX20:4","NX20:5","NX20:6","NX20:8","NX21:1","NX21:2","NX23:1","NX23:2","NX23:3","NX23:4","NX23:5","NX23:6","NX23:7","NX23:8","NX24:1","NX24:2","NX24:3","NX24:4","NX24:6","NX24:7","NX24:8","NX25:1","NX25:2"],"1":"RHzRtDn"},
{"x":3690,"y":446,"d":"EL211 Nrm","i":["NX20:1","NX20:2","NX20:3","NX20:4","NX20:5","NX23:1","NX23:2","NX23:3","NX23:4","NX23:5","NX23:6","NX23:7","NX23:8","NX24:1","NX24:2"],"1":"NVtLfUp"},
{"x":3690,"y":446,"d":"EL211 Rev","i":["NX20:6","NX20:8","NX21:1","NX21:2","NX24:3","NX24:4","NX24:6","NX24:7","NX24:8","NX25:1","NX25:2"],"1":"RVtLfUp"},
{"x":3690,"y":518,"d":"EL212 Nrm","i":["NX20:1","NX20:2","NX20:3","NX23:1","NX23:2","NX23:3","NX23:4","NX23:5","NX23:6"],"1":"NVtLfUp"},
{"x":3690,"y":518,"d":"EL212 Rev","i":["NX20:4","NX20:5","NX23:7","NX23:8","NX24:1","NX24:2"],"1":"RVtLfUp"},
{"x":3690,"y":566,"d":"EL213 Nrm","i":["NX20:1","NX20:2","NX23:1","NX23:2","NX23:3","NX23:4"],"1":"NVtLfUp"},
{"x":3690,"y":566,"d":"EL213 Rev","i":["NX20:3","NX23:5","NX23:6"],"1":"RVtLfUp"},
{"x":3690,"y":590,"d":"EL214 Nrm","i":["NX20:1","NX23:1","NX23:2"],"1":"NVtLfUp"},
{"x":3690,"y":590,"d":"EL214 Rev","i":["NX20:2","NX23:3","NX23:4"],"1":"RVtLfUp"},

{"x":410,"y":218,"d":"NL615 Nrm","i":["U304:5","U305:1"],"1":"NHzRtUp"},
{"x":410,"y":218,"d":"NL615 Rev","i":["U304:4","U305:2"],"1":"RHzRtUp"},
{"x":538,"y":218,"d":"NL616A Nrm","i":["U304:8","U305:4"],"1":"NHzLfDn"},
{"x":538,"y":218,"d":"NL616A Rev","i":["U305:1","U305:2","U305:5"],"1":"RHzLfDn"},
{"x":538,"y":250,"d":"NL616B Nrm","i":["U304:8","U305:4"],"1":"NHzRtUp"},
{"x":538,"y":250,"d":"NL616B Rev","i":["U305:1","U305:2","U305:5"],"1":"RHzRtUp"},
{"x":3850,"y":474,"d":"TL8038 Nrm","i":["X10E:8","X10F:1","X10F:2","X10F:3","X10F:4","X126:8","X127:1","X127:7"],"1":"NHzRtDn"},
{"x":3850,"y":474,"d":"TL8038 Rev","i":["X10E:6","X10E:7"],"1":"RHzRtDn"},
{"x":4002,"y":378,"d":"TL8045 Nrm","i":["X110:8","X111:1","X124:4","X124:5","X124:6","X124:7","X126:4","X126:5","X129:1","X129:4"],"1":"NHzLfDn"},
{"x":4002,"y":378,"d":"TL8045 Rev","i":["X111:2","X111:3","X129:2"],"1":"RHzLfDn"},
{"x":4002,"y":410,"d":"TL8046 Nrm","i":["X110:8","X111:1","X124:4","X124:5","X124:6","X124:7","X126:4","X126:5","X129:1","X129:4"],"1":"NHzRtUp"},
{"x":4002,"y":410,"d":"TL8046 Rev","i":["X111:2","X111:3","X129:2"],"1":"RHzRtUp"},
{"x":4010,"y":378,"d":"TL8047 Nrm","i":["X110:8","X111:1","X129:4"],"1":"NHzRtUp"},
{"x":4010,"y":378,"d":"TL8047 Rev","i":["X127:2","X127:3","X129:5"],"1":"RHzRtUp"}
],
"conditionals":[
{"i":"EL203_P","c":["AND","NX00:1","NX0D:2"]},
{"i":"EL203_M","c":["AND","NX00:1",["NOT","$_EL203_P"]]},
{"i":"EL205_P","c":["AND","NX00:2",["OR","NX0D:4","NX0D:6"]]},
{"i":"EL205_M","c":["AND","NX00:2",["NOT","$_EL205_P"]]},
{"i":"EL206_P","c":["AND","NX00:3",["OR","NX0E:1","NX0E:3","NX0E:5"]]},
{"i":"EL206_M","c":["AND","NX00:3",["NOT","$_EL206_P"]]},
{"i":"EL207_P","c":["AND","NX00:4",["OR","NX0E:7","NX0F:1"]]},
{"i":"EL207_M","c":["AND","NX00:4",["NOT","$_EL207_P"]]},
{"i":"EL208_P","c":["AND","NX00:5",["OR","NX0F:3","NX0F:5","NX0F:7"]]},
{"i":"EL208_M","c":["AND","NX00:5",["NOT","$_EL208_P"]]},
{"i":"EL209_P","c":["AND","NX00:6","NX10:1"]},
{"i":"EL209_M","c":["AND","NX00:6",["NOT","$_EL209_P"]]},
{"i":"EL210_P","c":["AND","NX00:7",["OR","NX10:3","NX10:5"]]},
{"i":"EL210_M","c":["AND","NX00:7",["NOT","$_EL210_P"]]},
{"i":"EL211_P","c":["AND","NX00:8","NX10:7"]},
{"i":"EL211_M","c":["AND","NX00:8",["NOT","$_EL211_P"]]},
{"i":"EL213_P","c":["AND","NX01:2","NX11:1"]},
{"i":"EL213_M","c":["AND","NX01:2",["NOT","$_EL213_P"]]},
{"i":"EL240_P","c":["AND","NX04:3","NX11:3"]},
{"i":"EL240_S","c":["AND","NX04:3",["OR","NX11:3","NX11:4"]]},
{"i":"EL240_M","c":["AND","NX04:3",["NOT","$_EL240_S"]]},
{"i":"EL242_P","c":["AND","NX04:5","NX11:7"]},
{"i":"EL242_M","c":["AND","NX04:5",["NOT","$_EL242_S"]]},
{"i":"EL243_P","c":["AND","NX04:6",["OR","NX12:1","NX12:3"]]},
{"i":"EL243_M","c":["AND","NX04:6",["NOT","$_EL243_P"]]},
{"i":"EL257_P","c":["AND","NX06:4","NX13:1"]},
{"i":"EL257_S","c":["AND","NX06:4",["OR","NX13:1","NX13:2"]]},
{"i":"EL257_M","c":["AND","NX06:4",["NOT","$_EL257_S"]]},
{"i":"EL258_P","c":["AND","NX06:5",["OR","NX13:4","NX13:6"]]},
{"i":"EL258_M","c":["AND","NX06:5",["NOT","$_EL258_P"]]},
{"i":"EL259_P","c":["AND","NX06:6","NX13:8"]},
{"i":"EL259_M","c":["AND","NX06:6",["NOT","$_EL259_P"]]},
{"i":"EL263_P","c":["AND","NX07:2",["OR","NX14:4","NX14:6"]]},
{"i":"EL263_M","c":["AND","NX07:2",["NOT","$_EL263_P"]]},
{"i":"EL264_P","c":["AND","NX07:3","NX14:8"]},
{"i":"EL264_M","c":["AND","NX07:3",["NOT","$_EL264_P"]]},
{"i":"EL266_P","c":["AND","NX07:5",["OR","NX15:3","NX15:5","NX15:7","NX16:1","NX16:3","NX16:5","NX16:7","NX17:1","NX17:3","NX17:5","NX17:7"]]},
{"i":"EL266_M","c":["AND","NX07:5",["NOT","$_EL266_P"]]},
{"i":"EL266_P","c":["AND","NX07:5",["OR","NX15:3","NX15:5","NX15:7","NX16:1","NX16:3","NX16:5","NX16:7","NX17:1","NX17:3","NX17:5","NX17:7"]]},
{"i":"EL266_M","c":["AND","NX07:5",["NOT","$_EL266_P"]]},
{"i":"EL267_P","c":["AND","NX07:6",["OR","NX18:5","NX18:7","NX19:1"]]},
{"i":"EL267_S","c":["AND","NX07:6",["OR","NX18:5","NX18:7","NX19:1","NX19:2","NX19:4","NX19:5","NX19:7"]]},
{"i":"EL267_M","c":["AND","NX07:6",["NOT","$_EL267_S"]]},
{"i":"EL268_P","c":["AND","NX07:7","NX1A:1"]},
{"i":"EL268_M","c":["AND","NX07:7",["NOT","$_EL268_P"]]},
{"i":"EL271_P","c":["AND","NX08:2","NX1A:4"]},
{"i":"EL271_M","c":["AND","NX08:2",["NOT","$_EL271_P"]]},
{"i":"EL273_P","c":["AND","NX08:3",["OR","NX1A:6","NX1A:8","NX2A:6"]]},
{"i":"EL273_S","c":["AND","NX08:3",["OR","NX1A:6","NX1A:8","NX2A:6","NX2B:1","NX2B:2","NX2B:5","NX2B:8","NX2C:3"]]},
{"i":"EL273_M","c":["AND","NX08:3",["NOT","$_EL273_S"]]},
{"i":"EL280_P","c":["AND","NX08:4","NX1B:4"]},
{"i":"EL280_M","c":["AND","NX08:4",["NOT","$_EL280_P"]]},
{"i":"EL281_P","c":["AND","NX08:5",["OR","NX1B:6","NX1B:8"]]},
{"i":"EL281_M","c":["AND","NX08:5",["NOT","$_EL281_P"]]},
{"i":"EL282_P","c":["AND","NX08:6","NX1C:2"]},
{"i":"EL282_M","c":["AND","NX08:6",["NOT","$_EL282_P"]]},
{"i":"EL283_P","c":["AND","NX08:7","NX1C:4"]},
{"i":"EL283_M","c":["AND","NX08:7",["NOT","$_EL283_P"]]},
{"i":"EL284_P","c":["AND","NX08:8","NX1C:6"]},
{"i":"EL284_M","c":["AND","NX08:8",["NOT","$_EL284_P"]]},
{"i":"EL285_P","c":["AND","NX09:1","NX1D:1"]},
{"i":"EL285_M","c":["AND","NX09:1",["NOT","$_EL285_P"]]},
{"i":"EL286_P","c":["AND","NX09:2",["OR","NX1D:4","NX1D:6"]]},
{"i":"EL286_S","c":["AND","NX09:2",["OR","NX1D:4","NX1D:5","NX1D:6"]]},
{"i":"EL286_M","c":["AND","NX09:2",["NOT","$_EL286_S"]]},
{"i":"EL287_P","c":["AND","NX09:3","NX1D:8"]},
{"i":"EL287_M","c":["AND","NX09:3",["NOT","$_EL287_P"]]},
{"i":"EL288_P","c":["AND","NX09:4",["OR","NX1E:2","NX1E:4"]]},
{"i":"EL288_S","c":["AND","NX09:4",["OR","NX1E:2","NX1E:3","NX1E:4"]]},
{"i":"EL288_M","c":["AND","NX09:4",["NOT","$_EL288_S"]]},
{"i":"EL290_P","c":["AND","NX09:6","NX1E:6"]},
{"i":"EL290_M","c":["AND","NX09:6",["NOT","$_EL290_P"]]},
{"i":"EL292","c":["AND","$_EL290_M","NX09!3","NX1D!7","NX1D!8"]},
{"i":"EL294_P","c":["AND","NX09:8","NX1E:8"]},
{"i":"EL294_M","c":["AND","NX09:8",["NOT","$_EL294_P"]]},
{"i":"EL296_P","c":["AND","NX0A:1",["OR","NX1F:2","NX1F:4"]]},
{"i":"EL296_S","c":["AND","NX0A:1",["OR","NX1F:2","NX1F:3","NX1F:4"]]},
{"i":"EL296_M","c":["AND","NX0A:1",["NOT","$_EL296_S"]]},
{"i":"EL298_P","c":["AND","NX0A:2","NX22:6"]},
{"i":"EL298_S","c":["AND","NX0A:2",["OR","NX20:1","NX20:2","NX20:3","NX20:4","NX20:5","NX20:6","NX21:1","NX21:2","NX21:5","NX21:8","NX22:3","NX22:4","NX22:6"]]},
{"i":"EL298_M","c":["AND","NX0A:2",["NOT","$_EL298_S"]]},
{"i":"EL300_P","c":["AND","NX0A:3",["OR","NX23:2","NX23:4","NX23:6","NX23:8","NX24:2","NX24:4","NX24:7","NX25:2","NX25:5","NX26:1","NX26:5","NX26:8","NX27:2"]]},
{"i":"EL300_S","c":["AND","NX0A:3",["OR","NX23:1","NX23:3","NX23:5","NX23:7","NX24:1","NX24:3","NX24:8","NX25:1","NX25:6","NX26:2","NX26:6","NX26:7","$_EL300_P"]]},
{"i":"EL300_M","c":["AND","NX0A:3",["NOT","$_EL300_S"]]},
{"i":"EL324_P","c":["AND","NX0A:7",["OR","NX27:6","NX27:8"]]},
{"i":"EL324_M","c":["AND","NX0A:7",["NOT","$_EL324_P"]]},
{"i":"EL325_P","c":["AND","NX0A:8","NX28:2"]},
{"i":"EL325_M","c":["AND","NX0A:8",["NOT","$_EL325_P"]]},
{"i":"EL327_P","c":["AND","NX0B:2","NX28:5"]},
{"i":"EL327_M","c":["AND","NX0B:2",["NOT","$_EL327_P"]]},
{"i":"EL350_P","c":["AND","NX0C:4","NX22:8"]},
{"i":"EL350_M","c":["AND","NX0C:4",["NOT","$_EL350_P"]]},
{"i":"NL1242_BR","c":["AND","U310:6","U31C:4"]},
{"i":"NL1254_1_BR","c":["AND","U311:5","U304:8"]},
{"i":"NL1254_2_BR","c":["AND","U311:5",["OR","U305:1","U305:2"]]},
{"i":"TL2444_P","c":["AND","X32C:8","X31B:5"]},
{"i":"TL2444_M","c":["AND","X32C:8",["NOT","$_TL2444_P"]]},
{"i":"TL2451_P","c":["AND","X32D:4","X31C:5"]},
{"i":"TL2451_M","c":["AND","X32D:4",["NOT","$_TL2451_P"]]},
{"i":"TL2546_P","c":["AND","X330:6",["OR","X31F:3","X31F:4"]]},
{"i":"TL2546_M","c":["AND","X330:6",["NOT","$_TL2546_P"]]},
{"i":"TL2559_P","c":["AND","X331:5","X320:4"]},
{"i":"TL2559_M","c":["AND","X331:5",["NOT","$_TL2559_P"]]},
{"i":"TL4018_P","c":["AND","X12C:4",["OR","X10E:7","X10F:2","X10F:4"]]},
{"i":"TL4018_S","c":["AND","X12C:4",["OR","X10E:7","X10E:8","X10F:2","X10F:4"]]},
{"i":"TL4018_M","c":["AND","X12C:4",["NOT","$_TL4018_S"]]},
{"i":"TL4027_P","c":["AND","X12D:2",["OR","X111:1","X111:3"]]},
{"i":"TL4027_M","c":["AND","X12D:2",["NOT","$_TL4027_P"]]},
{"i":"TL4446_P","c":["AND","X131:6",["OR","X122:4","X122:6","X122:8"]]},
{"i":"TL4446_S","c":["AND","X131:6",["OR","X122:2","X122:4","X122:6","X122:8"]]},
{"i":"TL4446_M","c":["AND","X131:6",["NOT","$_TL4446_S"]]},
{"i":"TL4455_P","c":["AND","X132:3","X124:7"]},
{"i":"TL4455_M","c":["AND","X132:3",["NOT","$_TL4455_P"]]},
{"i":"TL4629_P","c":["AND","X133:1","X127:3"]},
{"i":"TL4629_M","c":["AND","X133:1",["NOT","$_TL4629_P"]]}
],
"text":[
{"x":42,"y":226,"e":"CAMDEN\\nROAD","u":"nll2","t":"MNAV","g":1952},
{"x":2814,"y":230,"e":"CANADA\\nWATER","u":"ZCW","t":"MLOC"},
{"x":3402,"y":336,"e":"CANAL JN","u":"CANALJ","t":"LOC"},
{"x":551,"y":346,"e":"CANONBURY","u":"CNN","t":"LOC"},
{"x":978,"y":374,"e":"DALSTON\\nJUNCTION","u":"DLJ","t":"MLOC"},
{"x":195,"y":152,"e":"FINSBURY\\nPARK","u":"kingsx","t":"NAV","g":1354,"ga":"L"},
{"x":1364,"y":258,"e":"HAGGERSTON","u":"HGG","t":"LOC"},
{"x":214,"y":346,"e":"HIGHBURY &\\nISLINGTON","u":"HHY","t":"MLOC"},
{"x":1568,"y":258,"e":"HOXTON","u":"HOX","t":"LOC"},
{"x":3746,"y":202,"e":"LEWISHAM","u":"londonbridge","t":"MTEXT","g":3930},
{"x":1895,"y":350,"e":"GO TO\\nLIVERPOOL\\nSTREET","u":"livst","t":"NAV","g":962},
{"x":3482,"y":194,"e":"LONDON\\nBRIDGE","u":"londonbridge","t":"MTEXT","g":3930},
{"x":3754,"y":418,"e":"LONDON\\nBRIDGE","u":"londonbridge","t":"MTEXT","g":3594},
{"x":3596,"y":110,"e":"NEW CROSS","u":"NWX","t":"MLOC"},
{"x":3854,"y":286,"e":"NEW CROSS GATE","u":"NXG","t":"MLOC"},
{"x":3716,"y":372,"e":"NEW CROSS GATE\\nNORTH JN","u":"NEWXNJN","t":"LOC"},
{"x":3494,"y":500,"e":"NEW CROSS\\nGATE C.S.D","u":"NEWXCSD","t":"LOC"},
{"x":3803,"y":336,"e":"HEADSHUNT","u":"NEWXDHS","t":"LOC"},
{"x":3559,"y":338,"e":"WASH ROAD","u":"NEWXDWR","t":"LOC"},
{"x":4050,"y":418,"e":"NORWOOD\\nJUNCTION","u":"londonbridge","t":"MTEXT","g":3594},
{"x":2742,"y":418,"e":"QUEENS ROAD\\nPECKHAM","u":"londonbridge","t":"MTEXT","g":3148,"ga":"R"},
{"x":3495,"y":78,"e":"ROLT\\nSTREET JN","u":"ROLTSTJ","t":"LOC"},
{"x":2689,"y":254,"e":"ROTHERHITHE","u":"ROE","t":"LOC"},
{"x":2346,"y":254,"e":"SHADWELL","u":"SDE","t":"LOC"},
{"x":1809,"y":246,"e":"SHOREDITCH\\nHIGH STREET","u":"SDC","t":"LOC"},
{"x":3136,"y":270,"e":"SILWOOD JN","u":"SURRQSJ","t":"LOC"},
{"x":3202,"y":618,"e":"SILWOOD\\nSTABLING SIDINGS","u":"SURRQSS","t":"LOC"},
{"x":834,"y":234,"e":"STRATFORD","u":"nll2","t":"MNAV","g":1952},
{"x":3040,"y":250,"e":"SURREY\\nQUAYS","u":"SQE","t":"LOC"},
{"x":2048,"y":246,"e":"WHITECHAPEL","u":"ZLW","t":"MLOC"},
{"x":2573,"y":254,"e":"WAPPING","u":"WPE","t":"LOC"},
{"x":271,"y":330,"e":"1","t":"TEXT","c":"black"},
{"x":268,"y":274,"e":"2","t":"TEXT","c":"black"},
{"x":274,"y":266,"e":"7","t":"TEXT","c":"black"},
{"x":271,"y":210,"e":"8","t":"TEXT","c":"black"},
{"x":575,"y":330,"e":"1","t":"TEXT","c":"black"},
{"x":572,"y":274,"e":"2","t":"TEXT","c":"black"},
{"x":578,"y":266,"e":"3","t":"TEXT","c":"black"},
{"x":575,"y":210,"e":"4","t":"TEXT","c":"black"},
{"x":1020,"y":338,"e":"1","t":"TEXT","c":"black"},
{"x":1026,"y":330,"e":"2","t":"TEXT","c":"black"},
{"x":1020,"y":274,"e":"3","t":"TEXT","c":"black"},
{"x":1026,"y":266,"e":"4","t":"TEXT","c":"black"},
{"x":1391,"y":330,"e":"1","t":"TEXT","c":"black"},
{"x":1391,"y":274,"e":"2","t":"TEXT","c":"black"},
{"x":1583,"y":330,"e":"1","t":"TEXT","c":"black"},
{"x":1583,"y":274,"e":"2","t":"TEXT","c":"black"},
{"x":1839,"y":330,"e":"1","t":"TEXT","c":"black"},
{"x":1839,"y":274,"e":"2","t":"TEXT","c":"black"},
{"x":2111,"y":330,"e":"5","t":"TEXT","c":"black"},
{"x":2111,"y":274,"e":"6","t":"TEXT","c":"black"},
{"x":2367,"y":330,"e":"1","t":"TEXT","c":"black"},
{"x":2367,"y":274,"e":"2","t":"TEXT","c":"black"},
{"x":2591,"y":330,"e":"1","t":"TEXT","c":"black"},
{"x":2591,"y":274,"e":"2","t":"TEXT","c":"black"},
{"x":2719,"y":330,"e":"1","t":"TEXT","c":"black"},
{"x":2719,"y":274,"e":"2","t":"TEXT","c":"black"},
{"x":2847,"y":274,"e":"3","t":"TEXT","c":"black"},
{"x":2847,"y":330,"e":"4","t":"TEXT","c":"black"},
{"x":3055,"y":330,"e":"1","t":"TEXT","c":"black"},
{"x":3055,"y":274,"e":"2","t":"TEXT","c":"black"},
{"x":3644,"y":226,"e":"A","t":"TEXT","c":"black"},
{"x":3650,"y":218,"e":"B","t":"TEXT","c":"black"},
{"x":3644,"y":162,"e":"C","t":"TEXT","c":"black"},
{"x":3650,"y":154,"e":"D","t":"TEXT","c":"black"},
{"x":3935,"y":330,"e":"1","t":"TEXT","c":"black"},
{"x":3935,"y":370,"e":"2","t":"TEXT","c":"black"},
{"x":3932,"y":426,"e":"3","t":"TEXT","c":"black"},
{"x":3938,"y":434,"e":"4","t":"TEXT","c":"black"},
{"x":3935,"y":490,"e":"5","t":"TEXT","c":"black"}
]
}
