{
"panelUID":"shipley","panelName":"YKROC Leeds Northwest & Harrogate IECC","panelDescription":"Harrogate, Hellifield, Ilkley, & Bradford F.S. - Leeds","areas":["HG","Y2","Y3"],
"berths":[
{"x":1938,"y":202,"i":["HGLSDH"],"b":1},
{"x":2074,"y":202,"i":["HGH064"]},
{"x":3386,"y":170,"i":["Y23878"]},
{"x":3322,"y":202,"i":["Y23877"]},
{"x":3258,"y":202,"i":["Y23879"]},
{"x":3386,"y":202,"i":["Y23880"]},
{"x":3146,"y":170,"i":["Y23884"]},
{"x":3002,"y":170,"i":["Y23886"]},
{"x":2938,"y":170,"i":["HG3888"]},
{"x":3162,"y":202,"i":["HG4103"]},
{"x":3066,"y":202,"i":["HG4105"]},
{"x":3002,"y":202,"i":["HG4107"]},
{"x":2874,"y":170,"i":["HG4108"]},
{"x":2938,"y":202,"i":["HG4109"]},
{"x":2810,"y":202,"i":["HG4111","HG4110"]},
{"x":2810,"y":234,"i":["HG4112"]},
{"x":2810,"y":170,"i":["HG4113"]},
{"x":2730,"y":234,"i":["HG4114"]},
{"x":2730,"y":202,"i":["HG4116"]},
{"x":2730,"y":170,"i":["HG4118"]},
{"x":2666,"y":202,"i":["HG4119"]},
{"x":2538,"y":170,"i":["HG4122"]},
{"x":2554,"y":202,"i":["HG4123"]},
{"x":2346,"y":170,"i":["HG4130"]},
{"x":2410,"y":202,"i":["HG4131"]},
{"x":2186,"y":170,"i":["HG4134"]},
{"x":2234,"y":202,"i":["HG4135"]},
{"x":2026,"y":170,"i":["HG4138"]},

{"x":3386,"y":522,"i":["Y23890"]},
{"x":3386,"y":490,"i":["Y23892"]},
{"x":3322,"y":522,"i":["Y33893"]},
{"x":3258,"y":490,"i":["Y33894"]},
{"x":3258,"y":522,"i":["Y33895"]},
{"x":3194,"y":458,"i":["Y33896"]},
{"x":3130,"y":522,"i":["Y33897"]},
{"x":3194,"y":490,"i":["Y33898"]},
{"x":3130,"y":554,"i":["Y33899"]},
{"x":3050,"y":490,"i":["Y33904"]},
{"x":3050,"y":522,"i":["Y33907","Y34502"]},
{"x":2986,"y":490,"i":["Y33908"]},
{"x":2986,"y":522,"i":["Y33909"]},
{"x":2874,"y":490,"i":["Y33912"]},
{"x":2874,"y":522,"i":["Y33913"]},
{"x":2794,"y":490,"i":["Y33914"]},
{"x":2810,"y":522,"i":["Y33915"]},
{"x":2698,"y":490,"i":["Y33916"]},
{"x":2746,"y":522,"i":["Y33917"]},
{"x":2634,"y":490,"i":["Y33918"]},
{"x":2634,"y":522,"i":["Y33921","Y34504"]},
{"x":2538,"y":346,"i":["Y33922"]},
{"x":2538,"y":490,"i":["Y33924"]},
{"x":2554,"y":522,"i":["Y33925"]},
{"x":2474,"y":490,"i":["Y33926"]},
{"x":2490,"y":522,"i":["Y33927"]},
{"x":2410,"y":490,"i":["Y33928"]},
{"x":2410,"y":522,"i":["Y33929"]},
{"x":2330,"y":490,"i":["Y33932"]},
{"x":2330,"y":522,"i":["Y33933"]},
{"x":2266,"y":490,"i":["Y33934"]},
{"x":2298,"y":346,"i":["Y33935"]},
{"x":2202,"y":346,"i":["Y33937"]},
{"x":2202,"y":314,"i":["Y33938"]},
{"x":2202,"y":394,"i":["Y33939"]},
{"x":2122,"y":314,"i":["Y33942"]},
{"x":1978,"y":314,"i":["Y33943"]},
{"x":2042,"y":314,"i":["Y33944"]},
{"x":1978,"y":346,"i":["Y33945"]},
{"x":1834,"y":314,"i":["Y33948"]},
{"x":1834,"y":346,"i":["Y33951"]},
{"x":1722,"y":314,"i":["Y33952"]},
{"x":1722,"y":346,"i":["Y33953"]},
{"x":1594,"y":314,"i":["Y33954"]},
{"x":1538,"y":314,"i":["Y33955"]},
{"x":1458,"y":314,"i":["Y3A956"]},
{"x":1402,"y":314,"i":["Y3B956"]},
{"x":1338,"y":314,"i":["Y3R956"],"b":1},
{"x":1538,"y":346,"i":["Y33957"]},
{"x":1458,"y":346,"i":["Y3A958"]},
{"x":1402,"y":346,"i":["Y3B958"]},
{"x":1338,"y":346,"i":["Y3R958"],"b":1},
{"x":2266,"y":522,"i":["Y33961"]},
{"x":2138,"y":490,"i":["Y33962"]},
{"x":2266,"y":458,"i":["Y33963"]},
{"x":2138,"y":522,"i":["Y33964"]},
{"x":2074,"y":602,"i":["Y33965"]},
{"x":2138,"y":634,"i":["Y33966"]},
{"x":2074,"y":634,"i":["Y33967"]},
{"x":2074,"y":666,"i":["Y33969"]},
{"x":2074,"y":522,"i":["Y33971"]},
{"x":2074,"y":554,"i":["Y33973"]},
{"x":1946,"y":634,"i":["Y33976"]},
{"x":1946,"y":490,"i":["Y33978"]},
{"x":1962,"y":666,"i":["Y33981","Y34534"]},
{"x":1850,"y":634,"i":["Y33982"]},
{"x":1866,"y":666,"i":["Y33987"]},
{"x":1786,"y":634,"i":["Y33988","Y34537"]},
{"x":1722,"y":666,"i":["Y33991"]},
{"x":1642,"y":602,"i":["Y3A992"]},
{"x":1586,"y":602,"i":["Y3B992"]},
{"x":1522,"y":602,"i":["Y3R992"],"b":1},
{"x":1642,"y":634,"i":["Y3A994"]},
{"x":1586,"y":634,"i":["Y3B994"]},
{"x":1522,"y":634,"i":["Y3R994"],"b":1},
{"x":1642,"y":666,"i":["Y3A996"]},
{"x":1586,"y":666,"i":["Y3B996"]},
{"x":1522,"y":666,"i":["Y3R996"],"b":1},
{"x":1946,"y":522,"i":["Y34001"]},
{"x":1882,"y":522,"i":["Y34003"]},
{"x":1834,"y":490,"i":["Y34004"]},
{"x":1770,"y":522,"i":["Y34005"]},
{"x":1690,"y":490,"i":["Y34006"]},
{"x":1690,"y":522,"i":["Y34007"]},
{"x":1626,"y":490,"i":["Y34008"]},
{"x":1626,"y":522,"i":["Y34009"]},
{"x":1562,"y":490,"i":["Y34012","Y34543"]},
{"x":1562,"y":522,"i":["Y34013","Y34542"]},
{"x":1482,"y":522,"i":["Y34015","Y34544"]},
{"x":1418,"y":490,"i":["Y34014"]},
{"x":1354,"y":490,"i":["Y34016"]},
{"x":1418,"y":522,"i":["Y34017"]},
{"x":1354,"y":522,"i":["Y34019"]},
{"x":1290,"y":490,"i":["Y34022","Y34545"]},
{"x":1290,"y":522,"i":["Y34023"]},
{"x":1210,"y":490,"i":["Y34024"]},
{"x":1210,"y":522,"i":["Y34025","Y34546"]},
{"x":1098,"y":490,"i":["Y34026"]},
{"x":1098,"y":522,"i":["Y34027"]},
{"x":1034,"y":490,"i":["Y34028"]},
{"x":1034,"y":522,"i":["Y34029"]},
{"x":970,"y":522,"i":["Y34031","Y34548"]},
{"x":858,"y":458,"i":["Y3A032"]},
{"x":802,"y":458,"i":["Y3B032"]},
{"x":738,"y":460,"i":["Y3R032"],"b":1},
{"x":794,"y":490,"i":["Y34033"]},
{"x":858,"y":490,"i":["Y34034"]},
{"x":794,"y":522,"i":["Y34035"]},
{"x":858,"y":522,"i":["Y34036"]},
{"x":794,"y":554,"i":["Y34037"]},
{"x":858,"y":554,"i":["Y34038"]},
{"x":794,"y":586,"i":["Y34039"]},
{"x":866,"y":586,"i":["Y3LSRY"],"b":1},
{"x":714,"y":554,"i":["Y34042"]},
{"x":650,"y":554,"i":["Y34045"]},
{"x":650,"y":490,"i":["Y34046"]},
{"x":522,"y":490,"i":["Y34048"]},
{"x":410,"y":522,"i":["Y34049"]},
{"x":410,"y":490,"i":["Y34052"]},
{"x":3194,"y":554,"i":["Y34500"]},
{"x":3130,"y":458,"i":["Y34501"]},
{"x":1658,"y":346,"i":["Y34529","Y34520"]},
{"x":1978,"y":602,"i":["Y34532"]},
{"x":1906,"y":602,"i":["Y3LSCR"],"b":1},
{"x":1722,"y":634,"i":["Y34538","Y34539"]},
{"x":2010,"y":522,"i":["Y34540"]},
{"x":1546,"y":554,"i":["Y34541"]},
{"x":1618,"y":554,"i":["Y3LSKW"],"b":1},
{"x":970,"y":490,"i":["Y34549"]},
{"x":954,"y":554,"i":["Y34551"]},
{"x":1026,"y":554,"i":["Y3LSSS"],"b":1},
{"x":730,"y":442,"i":["Y34553"]},
{"x":650,"y":378,"i":["Y34554"]},
{"x":594,"y":378,"i":["Y3LSU3"],"b":1},
{"x":586,"y":490,"i":["Y34555"]},
{"x":650,"y":410,"i":["Y34556"]},
{"x":594,"y":410,"i":["Y3LSU2"],"b":1},
{"x":650,"y":442,"i":["Y34558"]},
{"x":594,"y":442,"i":["Y3LSU1"],"b":1},
{"x":586,"y":522,"i":["Y34564"]},
{"x":250,"y":490,"i":["Y3HF25"]},
{"x":298,"y":522,"i":["Y3HF42"]}
],
"signals":[
{"x":2384,"y":250,"d":"LUPCPR","i":["HG07:3"],"t":"TEXT","1":"RAISED"},
{"x":2381,"y":258,"d":"LDNCPR","i":["HG07:4"],"t":"TEXT","1":"LOWERED"},
{"x":2064,"y":222,"d":"H64","t":"NONE","iAu":1},
{"x":2072,"y":222,"d":"H64","t":"RIGHT","iSu":1,"iAu":1},
{"x":2152,"y":222,"d":"H65","t":"RIGHT","iRe":1,"iAu":1},
{"x":3160,"y":222,"d":"LH4103","i":"HG02:1","t":"RIGHT"},
{"x":3062,"y":222,"d":"LH4105","i":"HG02:2","t":"RIGHT"},
{"x":3000,"y":222,"d":"LH4107","i":"HG02:3","t":"RIGHT"},
{"x":2924,"y":166,"d":"LH4108","i":"HG02:4","t":"LEFT"},
{"x":2936,"y":222,"d":"LH4109","i":"HG02:5","t":"RIGHT","r":["HG00:1","HG00:2"]},
{"x":2862,"y":222,"d":"LH4110 LOS","t":"LEFT","iSh":1},
{"x":2798,"y":222,"d":"LH4111","i":"$_LH4111_M","t":"NONE","r":["HG00:4"]},
{"x":2806,"y":222,"d":"LH4111","i":"$_LH4111_S","t":"RIGHT","r":["HG00:3","HG00:4"],"iSu":1},
{"x":2808,"y":254,"d":"LH4112","i":"HG02:7","t":"RIGHT","r":["HG00:5"],"iSh":1},
{"x":2798,"y":166,"d":"LH4113","i":"$_LH4113_M","t":"NONE","r":["HG00:7"]},
{"x":2806,"y":166,"d":"LH4113","i":"$_LH4113_S","t":"RIGHT","r":["HG00:6","HG00:7"],"iSu":1},
{"x":2788,"y":254,"d":"LH4114","i":"$_LH4114_M","t":"NONE","r":["HG00:8"]},
{"x":2780,"y":254,"d":"LH4114","i":"$_LH4114_S","t":"LEFT","r":["HG00:8","HG01:1","HG01:2"],"iSu":1},
{"x":2780,"y":222,"d":"LH4116","i":"HG03:2","t":"LEFT","r":["HG01:3"],"iSh":1},
{"x":2780,"y":166,"d":"LH4118","i":"HG03:3","t":"LEFT","r":["HG01:4"]},
{"x":2716,"y":166,"d":"LH4120","i":"HG03:3","t":"LEFT","iRe":1},
{"x":2664,"y":222,"d":"LH4119","i":"HG03:4","t":"RIGHT"},
{"x":2624,"y":222,"d":"LH4121","i":"HG03:6","t":"RIGHT","iRe":1},
{"x":2588,"y":166,"d":"LH4122","i":"HG03:5","t":"LEFT"},
{"x":2552,"y":222,"d":"LH4123","i":"HG03:6","t":"RIGHT"},
{"x":2510,"y":166,"d":"LH4124","i":"HG03:5","t":"LEFT","iRe":1},
{"x":2470,"y":222,"d":"LH4129","i":"HG03:8","t":"RIGHT","iRe":1},
{"x":2396,"y":166,"d":"LH4130","i":"HG03:7","t":"LEFT","r":["HG01:5"]},
{"x":2408,"y":222,"d":"LH4131","i":"HG03:8","t":"RIGHT","r":["HG01:6"]},
{"x":2334,"y":166,"d":"LH4132","i":"HG03:7","t":"LEFT","iRe":1},
{"x":2294,"y":222,"d":"LH4133","i":"HG04:2","t":"RIGHT","iRe":1},
{"x":2236,"y":166,"d":"LH4134","i":"HG04:1","t":"LEFT"},
{"x":2232,"y":222,"d":"LH4135","i":"HG04:2","t":"RIGHT"},
{"x":2174,"y":166,"d":"LH4136","i":"HG04:1","t":"LEFT","iRe":1},
{"x":2076,"y":166,"d":"LH4138","i":"HG04:3","t":"LEFT"},
{"x":3320,"y":222,"d":"L3877","i":"Y254:3","t":"RIGHT"},
{"x":3436,"y":166,"d":"L3878","i":"Y254:4","t":"LEFT","r":["Y202:5"]},
{"x":3256,"y":222,"d":"L3879","t":"RIGHT","iAu":1},
{"x":3436,"y":222,"d":"L3880","i":"Y254:5","t":"LEFT","r":["Y202:6","Y202:7"]},
{"x":3308,"y":166,"d":"L3882","i":"$_L3882","t":"LEFT","iRe":1},
{"x":3196,"y":166,"d":"L3884","t":"LEFT","iAu":1},
{"x":3052,"y":166,"d":"L3886","t":"LEFT","iAu":1},
{"x":2988,"y":166,"d":"L3888","t":"LEFT","iAu":1},

{"x":300,"y":486,"d":"H25","t":"LEFT","iAu":1},
{"x":296,"y":542,"d":"H42","t":"RIGHT","iAu":1},
{"x":360,"y":542,"d":"H43","t":"RIGHT","iRe":1,"iAu":1},
{"x":1458,"y":330,"d":"L3956TRS","i":["Y335:8"],"t":"TEXT","1":"TRTS>"},
{"x":1458,"y":338,"d":"L3958TRS","i":["Y336:1"],"t":"TEXT","1":"TRTS>"},
{"x":1642,"y":618,"d":"L3992TRS","i":["Y335:5"],"t":"TEXT","1":"TRTS>"},
{"x":1642,"y":626,"d":"L3994TRS","i":["Y335:6"],"t":"TEXT","1":"TRTS>"},
{"x":1642,"y":682,"d":"L3996TRS","i":["Y335:7"],"t":"TEXT","1":"TRTS>"},
{"x":858,"y":450,"d":"L4032TRS","i":["Y334:6"],"t":"TEXT","1":"TRTS>"},
{"x":812,"y":506,"d":"L4033TRS","i":["Y334:7"],"t":"TEXT","1":"<TRTS"},
{"x":858,"y":506,"d":"L4034TRS","i":["Y334:8"],"t":"TEXT","1":"TRTS>"},
{"x":812,"y":514,"d":"L4035TRS","i":["Y335:1"],"t":"TEXT","1":"<TRTS"},
{"x":858,"y":514,"d":"L4036TRS","i":["Y335:2"],"t":"TEXT","1":"TRTS>"},
{"x":812,"y":570,"d":"L4037TRS","i":["Y335:3"],"t":"TEXT","1":"<TRTS"},
{"x":858,"y":570,"d":"L4038TRS","i":["Y335:4"],"t":"TEXT","1":"TRTS>"},
{"x":3436,"y":518,"d":"L3890","i":"Y254:6","t":"LEFT","r":["Y202:8","Y203:1","Y203:2"]},
{"x":3436,"y":486,"d":"L3892","i":"Y254:8","t":"LEFT","r":["Y203:4","Y203:5","Y203:6","Y203:7"]},
{"x":3320,"y":542,"d":"L3893","i":"Y32B:5","t":"RIGHT"},
{"x":3308,"y":486,"d":"L3894","i":"Y32C:6","t":"LEFT"},
{"x":3256,"y":542,"d":"L3895","i":"Y32C:7","t":"RIGHT","r":["Y315:3","Y315:4"]},
{"x":3244,"y":454,"d":"L3896","i":"Y32C:8","t":"LEFT","r":["Y315:5"]},
{"x":3128,"y":542,"d":"L3897","i":"Y32D:1","t":"RIGHT","r":["Y315:6"]},
{"x":3244,"y":486,"d":"L3898","i":"Y32D:2","t":"LEFT","r":["Y315:7"]},
{"x":3128,"y":574,"d":"L3899","i":"Y32D:3","t":"RIGHT","r":["Y315:8"]},
{"x":3100,"y":486,"d":"L3904","i":"Y32C:4","t":"LEFT","r":["Y316:1","Y316:2"]},
{"x":3068,"y":486,"d":"L3904BR","i":"Y32C:4","t":"LEFT","iBa":1},
{"x":3048,"y":542,"d":"L3907","i":"Y32C:5","t":"RIGHT"},
{"x":3036,"y":486,"d":"L3908","i":"Y32D:6","t":"LEFT"},
{"x":2984,"y":542,"d":"L3909","i":"Y32D:7","t":"RIGHT"},
{"x":2924,"y":486,"d":"L3912","i":"Y32D:8","t":"LEFT"},
{"x":2872,"y":542,"d":"L3913","i":"Y32E:1","t":"RIGHT"},
{"x":2920,"y":542,"d":"L3913BR","i":"Y32E:1","t":"RIGHT","iBa":1},
{"x":2844,"y":486,"d":"L3914","i":"Y32E:2","t":"LEFT"},
{"x":2808,"y":542,"d":"L3915","i":"Y32E:3","t":"RIGHT","f":["$_L3915_FA"]},
{"x":2748,"y":486,"d":"L3916","i":"Y32D:4","t":"LEFT"},
{"x":2744,"y":542,"d":"L3917","i":"Y32D:5","t":"RIGHT","r":["Y316:3"],"f":["$_L3917_FA"]},
{"x":2684,"y":486,"d":"L3918","i":"Y32E:6","t":"LEFT"},
{"x":2632,"y":542,"d":"L3921","i":"Y32E:7","t":"RIGHT","r":["Y316:4","Y316:5"]},
{"x":2596,"y":342,"d":"L3922","i":"$_L3922_M","t":"NONE"},
{"x":2588,"y":342,"d":"L3922","i":"$_L3922_S","t":"LEFT","r":["Y316:6","Y316:7"],"iSu":1},
{"x":2428,"y":342,"d":"L3922R","i":"$_L3922_R","t":"LEFT","iRe":1},
{"x":2596,"y":486,"d":"L3924","i":"$_L3924_M","t":"NONE"},
{"x":2588,"y":486,"d":"L3924","i":"$_L3924_S","t":"LEFT","r":["Y316:8","Y317:1"],"iSu":1},
{"x":2552,"y":542,"d":"L3925","i":"Y32F:2","t":"RIGHT"},
{"x":2526,"y":486,"d":"L3926","i":"Y32F:3","t":"LEFT"},
{"x":2486,"y":542,"d":"L3927","i":"Y32E:4","t":"RIGHT"},
{"x":2460,"y":486,"d":"L3928","i":"Y32E:5","t":"LEFT"},
{"x":2408,"y":542,"d":"L3929","i":"Y32F:4","t":"RIGHT"},
{"x":2380,"y":486,"d":"L3932","i":"Y326:1","t":"LEFT"},
{"x":2328,"y":542,"d":"L3933","i":"Y326:2","t":"RIGHT"},
{"x":2316,"y":486,"d":"L3934","i":"Y326:6","t":"LEFT"},
{"x":2296,"y":366,"d":"L3935","i":"Y32A:3","t":"RIGHT","r":["Y312:3"]},
{"x":2440,"y":366,"d":"L3935R","i":"Y32A:3","t":"RIGHT","iRe":1},
{"x":2200,"y":366,"d":"L3937","i":"Y329:4","t":"RIGHT","r":["Y312:4","Y312:5"]},
{"x":2252,"y":310,"d":"L3938","i":"Y329:5","t":"LEFT","r":["Y312:6"]},
{"x":2200,"y":414,"d":"L3939","i":"Y32A:6","t":"RIGHT","r":["Y312:7","Y312:8"]},
{"x":2296,"y":414,"d":"L3939R","i":"Y32A:6","t":"RIGHT","iRe":1},
{"x":2172,"y":310,"d":"L3942","i":"Y32A:7","t":"LEFT","r":["Y313:1","Y313:2"]},
{"x":1974,"y":310,"d":"L3943","t":"RIGHT"},
{"x":2120,"y":310,"d":"L3943R","t":"RIGHT","iRe":1},
{"x":2092,"y":310,"d":"L3944","i":"Y32B:1","t":"LEFT","r":["Y313:3"]},
{"x":1950,"y":310,"d":"L3944R","i":"Y32B:1","t":"LEFT","iRe":1},
{"x":1974,"y":366,"d":"L3945","i":"Y32B:2","t":"RIGHT"},
{"x":2120,"y":366,"d":"L3945R","i":"Y32B:2","t":"RIGHT","iRe":1},
{"x":1886,"y":310,"d":"L3948","i":"Y32B:3","t":"LEFT","r":["Y313:4"]},
{"x":1820,"y":310,"d":"L3948R","i":"Y32B:3","t":"LEFT","iRe":1},
{"x":1830,"y":366,"d":"L3951","i":"Y32A:4","t":"RIGHT"},
{"x":1910,"y":366,"d":"L3951R","i":"Y32A:4","t":"RIGHT","iRe":1},
{"x":1774,"y":310,"d":"L3952","i":"Y32A:5","t":"LEFT"},
{"x":1718,"y":366,"d":"L3953","i":"Y32B:6","t":"RIGHT","r":["Y313:5","Y313:6"]},
{"x":1784,"y":366,"d":"L3953R","i":"Y32B:6","t":"RIGHT","iRe":1},
{"x":1644,"y":310,"d":"L3954","i":"Y32B:7","t":"LEFT","r":["Y313:7"]},
{"x":1528,"y":310,"d":"L3955","i":"$_L3955_M","t":"NONE"},
{"x":1536,"y":310,"d":"L3955","i":"$_L3955_S","t":"RIGHT","r":["Y313:8","Y314:1","Y314:2","Y314:3"],"iSu":1},
{"x":1510,"y":310,"d":"L3956","i":"Y32C:1","t":"LEFT","r":["Y314:4"]},
{"x":1528,"y":366,"d":"L3957","i":"$_L3957_M","t":"NONE"},
{"x":1536,"y":366,"d":"L3957","i":"$_L3957_S","t":"RIGHT","r":["Y314:5","Y314:6"],"iSu":1},
{"x":1518,"y":366,"d":"L3958","i":"$_L3958_M","t":"NONE"},
{"x":1510,"y":366,"d":"L3958","i":"$_L3958_S","t":"LEFT","r":["Y314:7","Y314:8"],"iSu":1},
{"x":2264,"y":542,"d":"L3961","i":"Y326:7","t":"RIGHT","r":["Y30A:3","Y30A:4","Y30A:5","Y30A:6"]},
{"x":2190,"y":486,"d":"L3962","i":"Y326:8","t":"LEFT","r":["Y30A:7","Y30A:8"]},
{"x":2264,"y":478,"d":"L3963","i":"Y327:1","t":"RIGHT","r":["Y30B:1","Y30B:2","Y30B:3","Y30B:4","Y30B:5","Y30B:6","Y30B:7"]},
{"x":2344,"y":478,"d":"L3963R","i":"Y327:1","t":"RIGHT","iRe":1},
{"x":2188,"y":542,"d":"L3964","i":"Y327:2","t":"LEFT","r":["Y30B:8","Y30C:1","Y30C:2","Y30C:3"]},
{"x":2070,"y":622,"d":"L3965","i":"Y327:3","t":"RIGHT","r":["Y30C:4"]},
{"x":2188,"y":630,"d":"L3966","i":"Y326:4","t":"LEFT","r":["Y30C:5","Y30C:6","Y30C:7","Y30C:8"]},
{"x":2062,"y":630,"d":"L3967","i":"$_L3967_M","t":"NONE"},
{"x":2070,"y":630,"d":"L3967","i":"$_L3967_S","t":"RIGHT","r":["Y30D:1","Y30D:2"],"iSu":1},
{"x":2070,"y":686,"d":"L3969","i":"Y327:6","t":"RIGHT","r":["Y30D:3"]},
{"x":2072,"y":542,"d":"L3971","i":"Y327:7","t":"RIGHT","r":["Y30D:4"]},
{"x":2072,"y":550,"d":"L3973","i":"Y327:8","t":"RIGHT","r":["Y30D:5"]},
{"x":1996,"y":630,"d":"L3976","i":"Y328:1","t":"LEFT","r":["Y30D:6","Y30D:7","Y30D:8","Y30E:1"]},
{"x":1998,"y":486,"d":"L3978","i":"Y328:2","t":"LEFT","r":["Y30E:2","Y30E:3","Y30E:4","Y30E:5"]},
{"x":1960,"y":686,"d":"L3981","i":"Y328:3","t":"RIGHT"},
{"x":1900,"y":630,"d":"L3982","i":"Y327:4","t":"LEFT"},
{"x":1864,"y":686,"d":"L3987","i":"Y327:5","t":"RIGHT","r":["Y30E:6"]},
{"x":1836,"y":630,"d":"L3988","i":"Y328:6","t":"LEFT","r":["Y310:4"]},
{"x":1712,"y":686,"d":"L3991","i":"$_L3991_M","t":"NONE"},
{"x":1720,"y":686,"d":"L3991","i":"$_L3991_S","t":"RIGHT","r":["Y30E:7","Y30E:8","Y30F:1","Y30F:2","Y30F:3","Y30F:4"],"iSu":1},
{"x":1702,"y":598,"d":"L3992","i":"$_L3992_M","t":"NONE"},
{"x":1694,"y":598,"d":"L3992","i":"$_L3992_S","t":"LEFT","r":["Y30F:5","Y30F:6","Y30F:7"],"iSu":1},
{"x":1702,"y":654,"d":"L3994","i":"$_L3994_M","t":"NONE"},
{"x":1694,"y":654,"d":"L3994","i":"$_L3994_S","t":"LEFT","r":["Y30F:8","Y310:1","Y310:2"],"iSu":1},
{"x":1694,"y":662,"d":"L3996","i":"Y329:2","t":"LEFT","r":["Y310:3"]},
{"x":1942,"y":542,"d":"L4001","i":"Y329:3","t":"RIGHT"},
{"x":2000,"y":542,"d":"L4001BR","i":"Y329:3","t":"RIGHT","iBa":1},
{"x":1880,"y":542,"d":"L4003","i":"Y328:4","t":"RIGHT"},
{"x":1884,"y":486,"d":"L4004","i":"Y323:2","t":"LEFT"},
{"x":1766,"y":542,"d":"L4005","i":"Y323:3","t":"RIGHT","r":["Y307:6"]},
{"x":1742,"y":486,"d":"L4006","i":"Y323:4","t":"LEFT","r":["Y307:7"]},
{"x":1686,"y":542,"d":"L4007","i":"Y323:5","t":"RIGHT"},
{"x":1676,"y":486,"d":"L4008","i":"Y323:6","t":"LEFT"},
{"x":1624,"y":542,"d":"L4009","i":"Y323:7","t":"RIGHT","r":["Y307:8"]},
{"x":1614,"y":486,"d":"L4012","i":"Y323:8","t":"LEFT"},
{"x":1580,"y":486,"d":"L4012BR","i":"Y323:8","t":"LEFT","iBa":1},
{"x":1558,"y":542,"d":"L4013","i":"Y324:1","t":"RIGHT","r":["Y308:1"]},
{"x":1468,"y":486,"d":"L4014","i":"Y324:2","t":"LEFT","r":["Y308:2"]},
{"x":1480,"y":542,"d":"L4015","i":"Y324:3","t":"RIGHT"},
{"x":1406,"y":486,"d":"L4016","i":"Y324:4","t":"LEFT"},
{"x":1416,"y":542,"d":"L4017","i":"Y324:5","t":"RIGHT","r":["Y308:3"]},
{"x":1350,"y":542,"d":"L4019","i":"Y324:6","t":"RIGHT"},
{"x":1340,"y":486,"d":"L4022","i":"Y324:7","t":"LEFT","r":["Y308:4"]},
{"x":1288,"y":542,"d":"L4023","i":"Y324:8","t":"RIGHT","r":["Y308:5"]},
{"x":1260,"y":486,"d":"L4024","i":"Y325:3","t":"LEFT","r":["Y308:6"]},
{"x":1208,"y":542,"d":"L4025","i":"Y325:1","t":"RIGHT","r":["Y308:7"]},
{"x":1148,"y":486,"d":"L4026","i":"Y325:2","t":"LEFT","r":["Y308:8"]},
{"x":1096,"y":542,"d":"L4027","i":"Y325:4","t":"RIGHT"},
{"x":1084,"y":486,"d":"L4028","i":"Y320:2","t":"LEFT"},
{"x":1032,"y":542,"d":"L4029","i":"Y320:3","t":"RIGHT","r":["Y300:1"]},
{"x":960,"y":542,"d":"L4031","i":"$_L4031_M","t":"NONE"},
{"x":968,"y":542,"d":"L4031","i":"$_L4031_S","t":"RIGHT","r":["Y300:2","Y300:3","Y300:4","Y300:5","Y300:6","Y300:7","Y300:8","Y301:1"],"iSu":1},
{"x":908,"y":454,"d":"L4032","i":"Y320:5","t":"LEFT","r":["Y301:2"]},
{"x":782,"y":486,"d":"L4033","t":"NONE"},
{"x":790,"y":486,"d":"L4033","i":"Y320:6","t":"RIGHT","r":["Y301:3","Y301:4","Y301:5","Y301:6"],"iSu":1},
{"x":910,"y":486,"d":"L4034","i":"Y320:7","t":"LEFT","r":["Y301:7"]},
{"x":782,"y":542,"d":"L4035","i":"$_L4035_M","t":"NONE"},
{"x":790,"y":542,"d":"L4035","i":"$_L4035_S","t":"RIGHT","r":["Y301:8","Y302:1","Y302:2","Y302:3","Y302:4"],"iSu":1},
{"x":824,"y":542,"d":"L4035BR","i":"Y320:8","t":"RIGHT","iBa":1},
{"x":918,"y":542,"d":"L4036","i":"$_L4036_M","t":"NONE"},
{"x":910,"y":542,"d":"L4036","i":"$_L4036_S","t":"LEFT","r":["Y302:5","Y302:6"],"iSu":1},
{"x":784,"y":574,"d":"L4037","i":"$_L4037_M","t":"NONE"},
{"x":792,"y":574,"d":"L4037","i":"$_L4037_S","t":"RIGHT","r":["Y302:7","Y302:8"],"iSu":1},
{"x":918,"y":550,"d":"L4038","i":"$_L4038_M","t":"NONE"},
{"x":910,"y":550,"d":"L4038","i":"$_L4038_S","t":"LEFT","r":["Y303:1","Y303:2","Y303:3"],"iSu":1},
{"x":792,"y":606,"d":"L4039","i":"Y321:4","t":"RIGHT","r":["Y303:4"]},
{"x":832,"y":606,"d":"L4039R","t":"RIGHT","iDB":1},
{"x":764,"y":550,"d":"L4042","i":"Y321:5","t":"LEFT","r":["Y303:5","Y303:6"]},
{"x":648,"y":574,"d":"L4045","i":"Y321:6","t":"RIGHT","r":["Y303:7"]},
{"x":708,"y":486,"d":"L4046","i":"$_L4046_M","t":"NONE"},
{"x":700,"y":486,"d":"L4046","i":"$_L4046_S","t":"LEFT","r":["Y303:8","Y304:1","Y304:2","Y304:3"],"iSu":1},
{"x":572,"y":486,"d":"L4048","i":"Y321:8","t":"LEFT","r":["Y304:4"]},
{"x":508,"y":486,"d":"L4048R","i":"Y321:8","t":"LEFT","iRe":1},
{"x":406,"y":542,"d":"L4049","i":"Y322:1","t":"RIGHT","r":["Y304:5"]},
{"x":472,"y":542,"d":"L4049R","i":"Y322:1","t":"RIGHT","iRe":1},
{"x":462,"y":486,"d":"L4052","i":"Y322:2","t":"LEFT","r":["Y304:6"]},
{"x":396,"y":486,"d":"L4052R","i":"Y322:2","t":"LEFT","iRe":1},
{"x":3244,"y":550,"d":"L4500 LOS","t":"LEFT","iSh":1},
{"x":3128,"y":478,"d":"L4501","i":"Y32F:5","t":"RIGHT","r":["Y317:2"],"iSh":1},
{"x":3100,"y":542,"d":"L4502","i":"Y32F:6","t":"LEFT","r":["Y317:3","Y317:4","Y317:5"],"iSh":1},
{"x":2684,"y":542,"d":"L4504 LOS","t":"LEFT","iSh":1},
{"x":1708,"y":366,"d":"L4520 LOS","t":"LEFT","iSh":1},
{"x":1656,"y":366,"d":"L4529","i":"Y32B:4","t":"RIGHT","r":["Y315:1","Y315:2"],"iSh":1},
{"x":2028,"y":598,"d":"L4532","i":"Y328:5","t":"LEFT","r":["Y310:5","Y310:6"],"iSh":1},
{"x":2012,"y":686,"d":"L4534","i":"Y329:6","t":"LEFT","r":["Y310:7","Y310:8"],"iSh":1},
{"x":1784,"y":630,"d":"L4537","i":"Y329:7","t":"RIGHT","r":["Y311:1","Y311:2"],"iSh":1},
{"x":1772,"y":630,"d":"L4538","i":"Y329:8","t":"LEFT","r":["Y311:3"],"iSh":1},
{"x":1720,"y":630,"d":"L4539","i":"Y32A:1","t":"RIGHT","r":["Y311:4","Y311:5"],"iSh":1},
{"x":2060,"y":542,"d":"L4540","i":"Y32A:2","t":"LEFT","r":["Y311:6","Y311:7"],"iSh":1},
{"x":1544,"y":574,"d":"L4541","i":"Y325:5","t":"RIGHT","r":["Y309:1"],"iSh":1},
{"x":1614,"y":542,"d":"L4542 LOS","t":"LEFT","iSh":1},
{"x":1558,"y":486,"d":"L4543","i":"Y325:6","t":"RIGHT","r":["Y309:2"],"iSh":1},
{"x":1532,"y":542,"d":"L4544","i":"Y325:7","t":"LEFT","r":["Y309:3","Y309:4","Y309:5"],"iSh":1},
{"x":1288,"y":486,"d":"L4545","i":"Y325:8","t":"RIGHT","r":["Y309:6"],"iSh":1},
{"x":1260,"y":542,"d":"L4546","i":"Y326:3","t":"LEFT","r":["Y309:7"],"iSh":1},
{"x":1020,"y":542,"d":"L4548 LOS","t":"LEFT","iSh":1},
{"x":968,"y":486,"d":"L4549","i":"Y322:3","t":"RIGHT","r":["Y304:7","Y304:8","Y305:1","Y305:2"],"iSh":1},
{"x":952,"y":574,"d":"L4551","i":"Y322:4","t":"RIGHT","r":["Y305:3"],"iSh":1},
{"x":728,"y":438,"d":"L4553","i":"Y322:5","t":"RIGHT","r":["Y305:4","Y305:5","Y305:6"],"iSh":1},
{"x":700,"y":374,"d":"L4554","i":"Y322:6","t":"LEFT","r":["Y305:7","Y305:8","Y306:1"],"iSh":1},
{"x":584,"y":486,"d":"L4555 LOS","t":"RIGHT","iSh":1},
{"x":700,"y":406,"d":"L4556","i":"Y322:7","t":"LEFT","r":["Y306:2","Y306:3","Y306:4"],"iSh":1},
{"x":700,"y":438,"d":"L4558","i":"Y322:8","t":"LEFT","r":["Y306:5","Y306:6","Y306:7"],"iSh":1},
{"x":636,"y":542,"d":"L4564","i":"Y323:1","t":"LEFT","r":["Y306:8","Y307:1"],"iSh":1},
{"x":580,"y":542,"d":"L4564R","i":"Y323:1","t":"LEFT","iSu":1},
{"x":850,"y":497,"d":"TES","i":["Y336!3"],"t":"TRACKC","w":56},
{"x":804,"y":465,"d":"TET","i":["Y336!4"],"t":"TRACKC","w":102},
{"x":794,"y":497,"d":"TES","i":["Y336!5"],"t":"TRACKC","w":56},
{"x":1588,"y":609,"d":"TGA","i":["Y339!5"],"t":"TRACKC","w":50},
{"x":1638,"y":609,"d":"TGB","i":["Y339!6"],"t":"TRACKC","w":52},
{"x":1588,"y":641,"d":"THA","i":["Y33A!4"],"t":"TRACKC","w":50},
{"x":1588,"y":673,"d":"THB","i":["Y33A!5"],"t":"TRACKC","w":50},
{"x":1638,"y":641,"d":"THC","i":["Y33A!6"],"t":"TRACKC","w":52},
{"x":1638,"y":673,"d":"THD","i":["Y33A!7"],"t":"TRACKC","w":52},
{"x":1404,"y":321,"d":"TKJ","i":["Y33B!2"],"t":"TRACKC","w":50},
{"x":1454,"y":321,"d":"TKK","i":["Y33B!3"],"t":"TRACKC","w":52},
{"x":1404,"y":353,"d":"TKL","i":["Y33B!4"],"t":"TRACKC","w":50},
{"x":1454,"y":353,"d":"TKM","i":["Y33B!5"],"t":"TRACKC","w":52},
{"x":850,"y":561,"d":"TNB","i":["Y337!7"],"t":"TRACKC","w":56},
{"x":794,"y":561,"d":"TNC","i":["Y337!8"],"t":"TRACKC","w":56},
{"x":850,"y":529,"d":"TPT","i":["Y338!3"],"t":"TRACKC","w":56},
{"x":794,"y":529,"d":"TPU","i":["Y338!4"],"t":"TRACKC","w":56}
],
"points":[
{"x":2794,"y":170,"d":"LH5171A Nrm","i":["HG00:1","HG00:3","HG00:4","HG01:1","HG01:4"],"1":"NHzRtDn"},
{"x":2794,"y":170,"d":"LH5171A Rev","i":["HG00:6","HG00:7","HG00:8","HG01:3"],"1":"RHzRtDn"},
{"x":2794,"y":202,"d":"LH5171B Nrm","i":["HG00:1","HG00:3","HG00:4","HG01:1","HG01:4"],"1":"NHzLfUp"},
{"x":2794,"y":202,"d":"LH5171B Rev","i":["HG00:6","HG00:7","HG00:8","HG01:3"],"1":"RHzLfUp"},
{"x":2778,"y":202,"d":"LH5172A Nrm","i":["HG00:4","HG00:5","HG00:7","HG01:3"],"1":"NHzRtDn"},
{"x":2778,"y":202,"d":"LH5172A Rev","i":["HG00:3","HG00:6","HG00:8","HG01:1","HG01:2"],"1":"RHzRtDn"},
{"x":2778,"y":234,"d":"LH5172B Nrm","i":["HG00:4","HG00:5","HG00:7","HG01:3"],"1":"NHzLfUp"},
{"x":2778,"y":234,"d":"LH5172B Rev","i":["HG00:3","HG00:6","HG00:8","HG01:1","HG01:2"],"1":"RHzLfUp"},
{"x":2794,"y":234,"d":"LH5173 Nrm","i":["HG00:3","HG00:6","HG00:8","HG01:1"],"1":"NHzLfDn"},
{"x":2794,"y":234,"d":"LH5173 Rev","i":["HG00:5","HG01:2"],"1":"RHzLfDn"},

{"x":3242,"y":490,"d":"L5103 Nrm","i":["Y315:7"],"1":"NHzRtUp"},
{"x":3242,"y":490,"d":"L5103 Rev","i":["Y315:5"],"1":"RHzRtUp"},
{"x":3242,"y":522,"d":"L5104 Nrm","i":["Y315:4"],"1":"NHzRtDn"},
{"x":3242,"y":522,"d":"L5104 Rev","i":["Y315:3"],"1":"RHzRtDn"},
{"x":3114,"y":458,"d":"L5105A Nrm","i":["Y316:2","Y317:4"],"1":"NHzRtDn"},
{"x":3114,"y":458,"d":"L5105A Rev","i":["Y316:1","Y317:2","Y317:3"],"1":"RHzRtDn"},
{"x":3114,"y":490,"d":"L5105B Nrm","i":["Y316:2","Y317:4"],"1":"NHzLfUp"},
{"x":3114,"y":490,"d":"L5105B Rev","i":["Y316:1","Y317:2","Y317:3"],"1":"RHzLfUp"},
{"x":3114,"y":554,"d":"L5106A Nrm","i":["Y315:6"],"1":"NHzRtUp"},
{"x":3114,"y":554,"d":"L5106A Rev","i":["Y315:8","Y317:5"],"1":"RHzRtUp"},
{"x":3114,"y":522,"d":"L5106B Nrm","i":["Y315:6"],"1":"NHzLfDn"},
{"x":3114,"y":522,"d":"L5106B Rev","i":["Y315:8","Y317:5"],"1":"RHzLfDn"},
{"x":3098,"y":490,"d":"L5107A Nrm","i":["Y315:6","Y315:8","Y316:1","Y316:2","Y317:5"],"1":"NHzRtDn"},
{"x":3098,"y":490,"d":"L5107A Rev","i":["Y317:2","Y317:3","Y317:4"],"1":"RHzRtDn"},
{"x":3098,"y":522,"d":"L5107B Nrm","i":["Y315:6","Y315:8","Y316:1","Y316:2","Y317:5"],"1":"NHzLfUp"},
{"x":3098,"y":522,"d":"L5107B Rev","i":["Y317:2","Y317:3","Y317:4"],"1":"RHzLfUp"},
{"x":2618,"y":522,"d":"L5108A Nrm","i":["Y316:4","Y316:6","Y316:8"],"1":"NHzRtUp"},
{"x":2618,"y":522,"d":"L5108A Rev","i":["Y316:5","Y316:7","Y317:1"],"1":"RHzRtUp"},
{"x":2618,"y":490,"d":"L5108B Nrm","i":["Y316:4","Y316:6","Y316:8"],"1":"NHzLfDn"},
{"x":2618,"y":490,"d":"L5108B Rev","i":["Y316:5","Y316:7","Y317:1"],"1":"RHzLfDn"},
{"x":2602,"y":490,"d":"L5109 Nrm","i":["Y316:8","Y317:1"],"1":"NHzRtUp"},
{"x":2602,"y":490,"d":"L5109 Rev","i":["Y316:5","Y316:6","Y316:7"],"1":"RHzRtUp"},
{"x":2282,"y":346,"d":"L5111 Nrm","i":["Y312:3"],"1":"NHzRtUp"},
{"x":2282,"y":346,"d":"L5111 Rev","i":["Y312:6"],"1":"RHzRtUp"},
{"x":2186,"y":346,"d":"L5112 Nrm","i":["Y312:4","Y312:5"],"1":"NHzLfDn"},
{"x":2186,"y":346,"d":"L5112 Rev","i":["Y312:7","Y312:8","Y313:2"],"1":"RHzLfDn"},
{"x":2170,"y":346,"d":"L5113A Nrm","i":["Y312:4","Y312:7","Y313:1"],"1":"NHzRtUp"},
{"x":2170,"y":346,"d":"L5113A Rev","i":["Y312:5","Y312:8","Y313:2"],"1":"RHzRtUp"},
{"x":2170,"y":314,"d":"L5113B Nrm","i":["Y312:4","Y312:7","Y313:1"],"1":"NHzLfDn"},
{"x":2170,"y":314,"d":"L5113B Rev","i":["Y312:5","Y312:8","Y313:2"],"1":"RHzLfDn"},
{"x":1642,"y":346,"d":"L5114A Nrm","i":["Y313:5","Y313:7","Y314:4","Y314:7","Y314:8","Y315:1"],"1":"NHzRtUp"},
{"x":1642,"y":346,"d":"L5114A Rev","i":["Y313:6","Y315:2"],"1":"RHzRtUp"},
{"x":1642,"y":314,"d":"L5114B Nrm","i":["Y313:5","Y313:7","Y314:4","Y314:7","Y314:8","Y315:1"],"1":"NHzLfDn"},
{"x":1642,"y":314,"d":"L5114B Rev","i":["Y313:6","Y315:2"],"1":"RHzLfDn"},
{"x":1514,"y":314,"d":"L5115A Nrm","i":["Y313:5","Y314:2","Y314:3","Y314:4","Y314:5","Y314:6","Y314:8"],"1":"NHzRtDn"},
{"x":1514,"y":314,"d":"L5115A Rev","i":["Y313:8","Y314:1","Y314:7"],"1":"RHzRtDn"},
{"x":1514,"y":346,"d":"L5115B Nrm","i":["Y313:5","Y314:2","Y314:3","Y314:4","Y314:5","Y314:6","Y314:8"],"1":"NHzLfUp"},
{"x":1514,"y":346,"d":"L5115B Rev","i":["Y313:8","Y314:1","Y314:7"],"1":"RHzLfUp"},
{"x":2250,"y":490,"d":"L5117 Nrm","i":["Y30A:8","Y30C:2","Y30C:3","Y30C:7","Y30C:8"],"1":"NHzLfUp"},
{"x":2250,"y":490,"d":"L5117 Rev","i":["Y30A:7","Y30B:1","Y30B:2","Y30B:3","Y30B:4","Y30B:5","Y30B:6","Y30B:7","Y30B:8","Y30C:1","Y30C:5","Y30C:6"],"1":"RHzLfUp"},
{"x":2234,"y":490,"d":"L5118A Nrm","i":["Y30A:3","Y30A:4","Y30A:5","Y30A:6","Y30A:7","Y30A:8","Y30B:3","Y30B:6","Y30B:7","Y30B:8","Y30C:2","Y30C:5","Y30C:7"],"1":"NHzRtDn"},
{"x":2234,"y":490,"d":"L5118A Rev","i":["Y30B:1","Y30B:2","Y30B:4","Y30B:5","Y30C:1","Y30C:3","Y30C:6","Y30C:8"],"1":"RHzRtDn"},
{"x":2234,"y":522,"d":"L5118B Nrm","i":["Y30A:3","Y30A:4","Y30A:5","Y30A:6","Y30A:7","Y30A:8","Y30B:3","Y30B:6","Y30B:7","Y30B:8","Y30C:2","Y30C:5","Y30C:7"],"1":"NHzLfUp"},
{"x":2234,"y":522,"d":"L5118B Rev","i":["Y30B:1","Y30B:2","Y30B:4","Y30B:5","Y30C:1","Y30C:3","Y30C:6","Y30C:8"],"1":"RHzLfUp"},
{"x":2218,"y":522,"d":"L5119 Nrm","i":["Y30A:4","Y30A:5","Y30A:6","Y30B:2","Y30B:4","Y30B:5","Y30C:1","Y30C:3","Y30C:6","Y30C:8"],"1":"NHzRtDn"},
{"x":2218,"y":522,"d":"L5119 Rev","i":["Y30A:3","Y30B:1"],"1":"RHzRtDn"},
{"x":2202,"y":490,"d":"L5120A Nrm","i":["Y30A:4","Y30A:5","Y30A:6","Y30A:7","Y30A:8","Y30B:2","Y30B:4","Y30B:5","Y30C:1","Y30C:3","Y30C:6","Y30C:8"],"1":"NHzRtDn"},
{"x":2202,"y":490,"d":"L5120A Rev","i":["Y30B:3","Y30B:6","Y30B:7","Y30B:8","Y30C:2","Y30C:5","Y30C:7"],"1":"RHzRtDn"},
{"x":2202,"y":522,"d":"L5120B Nrm","i":["Y30A:4","Y30A:5","Y30A:6","Y30A:7","Y30A:8","Y30B:2","Y30B:4","Y30B:5","Y30C:1","Y30C:3","Y30C:6","Y30C:8"],"1":"NHzLfUp"},
{"x":2202,"y":522,"d":"L5120B Rev","i":["Y30B:3","Y30B:6","Y30B:7","Y30B:8","Y30C:2","Y30C:5","Y30C:7"],"1":"RHzLfUp"},
{"x":2186,"y":522,"d":"L5121 Nrm","i":["Y30A:5","Y30A:6","Y30B:4","Y30B:5","Y30B:6","Y30B:7","Y30B:8","Y30C:1","Y30C:2","Y30C:3"],"1":"NHzRtDn"},
{"x":2186,"y":522,"d":"L5121 Rev","i":["Y30A:4","Y30B:2","Y30B:3","Y30C:5","Y30C:6","Y30C:7","Y30C:8","Y30D:8"],"1":"RHzRtDn"},
{"x":2042,"y":634,"d":"L5122 Nrm","i":["Y30A:4","Y30B:2","Y30B:3","Y30D:1","Y30D:2","Y30D:8","Y30E:1","Y310:6","Y310:8"],"1":"NHzLfUp"},
{"x":2042,"y":634,"d":"L5122 Rev","i":["Y30C:4","Y30D:6","Y30D:7","Y30E:4","Y310:5","Y310:7"],"1":"RHzLfUp"},
{"x":2026,"y":634,"d":"L5123A Nrm","i":["Y30A:4","Y30B:2","Y30B:3","Y30C:4","Y30D:1","Y30D:6","Y30D:7","Y30D:8","Y30E:1","Y30E:4","Y310:7","Y310:8"],"1":"NHzRtUp"},
{"x":2026,"y":634,"d":"L5123A Rev","i":["Y30D:2","Y310:5","Y310:6"],"1":"RHzRtUp"},
{"x":2026,"y":602,"d":"L5123B Nrm","i":["Y30A:4","Y30B:2","Y30B:3","Y30C:4","Y30D:1","Y30D:6","Y30D:7","Y30D:8","Y30E:1","Y30E:4","Y310:7","Y310:8"],"1":"NHzLfDn"},
{"x":2026,"y":602,"d":"L5123B Rev","i":["Y30D:2","Y310:5","Y310:6"],"1":"RHzLfDn"},
{"x":2010,"y":634,"d":"L5124A Nrm","i":["Y30D:3","Y30D:6","Y30D:7","Y30D:8","Y30E:1"],"1":"NHzRtDn"},
{"x":2010,"y":634,"d":"L5124A Rev","i":["Y30C:4","Y30D:1","Y310:7","Y310:8"],"1":"RHzRtDn"},
{"x":2010,"y":666,"d":"L5124B Nrm","i":["Y30D:3","Y30D:6","Y30D:7","Y30D:8","Y30E:1"],"1":"NHzLfUp"},
{"x":2010,"y":666,"d":"L5124B Rev","i":["Y30C:4","Y30D:1","Y310:7","Y310:8"],"1":"RHzLfUp"},
{"x":1770,"y":634,"d":"L5128A Nrm","i":["Y30E:6","Y30F:5","Y30F:8","Y311:2","Y311:3"],"1":"NHzRtDn"},
{"x":1770,"y":634,"d":"L5128A Rev","i":["Y30F:6","Y310:1","Y310:3","Y311:1"],"1":"RHzRtDn"},
{"x":1770,"y":666,"d":"L5128B Nrm","i":["Y30E:6","Y30F:5","Y30F:8","Y311:2","Y311:3"],"1":"NHzLfUp"},
{"x":1770,"y":666,"d":"L5128B Rev","i":["Y30F:6","Y310:1","Y310:3","Y311:1"],"1":"RHzLfUp"},
{"x":1706,"y":666,"d":"L5129A Nrm","i":["Y30E:7","Y30E:8","Y30F:5","Y30F:7","Y30F:8","Y310:2","Y310:3","Y311:4","Y311:5"],"1":"NHzRtUp"},
{"x":1706,"y":666,"d":"L5129A Rev","i":["Y30F:1","Y30F:2","Y30F:3","Y30F:4","Y30F:6","Y310:1"],"1":"RHzRtUp"},
{"x":1706,"y":634,"d":"L5129B Nrm","i":["Y30E:7","Y30E:8","Y30F:5","Y30F:7","Y30F:8","Y310:2","Y310:3","Y311:4","Y311:5"],"1":"NHzLfDn"},
{"x":1706,"y":634,"d":"L5129B Rev","i":["Y30F:1","Y30F:2","Y30F:3","Y30F:4","Y30F:6","Y310:1"],"1":"RHzLfDn"},
{"x":1690,"y":634,"d":"L5130 Nrm","i":["Y30F:1","Y30F:2","Y30F:8","Y310:1","Y310:2","Y311:4"],"1":"NHzRtUp"},
{"x":1690,"y":634,"d":"L5130 Rev","i":["Y30F:3","Y30F:4","Y30F:5","Y30F:6","Y30F:7","Y311:5"],"1":"RHzRtUp"},
{"x":2058,"y":522,"d":"L5132 Nrm","i":["Y30A:5","Y30B:4","Y30B:6","Y30D:4","Y30E:3","Y311:6"],"1":"NHzLfDn"},
{"x":2058,"y":522,"d":"L5132 Rev","i":["Y30D:5","Y30D:6","Y30E:4","Y30E:5","Y311:7"],"1":"RHzLfDn"},
{"x":1994,"y":522,"d":"L5133A Nrm","i":["Y30D:4","Y30D:5","Y30E:2"],"1":"NHzRtUp"},
{"x":1994,"y":522,"d":"L5133A Rev","i":["Y30E:3","Y30E:4","Y30E:5"],"1":"RHzRtUp"},
{"x":1994,"y":490,"d":"L5133B Nrm","i":["Y30D:4","Y30D:5","Y30E:2"],"1":"NHzLfDn"},
{"x":1994,"y":490,"d":"L5133B Rev","i":["Y30E:3","Y30E:4","Y30E:5"],"1":"RHzLfDn"},
{"x":1546,"y":490,"d":"L5135A Nrm","i":["Y308:1","Y308:2","Y309:4"],"1":"NHzRtDn"},
{"x":1546,"y":490,"d":"L5135A Rev","i":["Y309:2","Y309:3"],"1":"RHzRtDn"},
{"x":1546,"y":522,"d":"L5135B Nrm","i":["Y308:1","Y308:2","Y309:4"],"1":"NHzLfUp"},
{"x":1546,"y":522,"d":"L5135B Rev","i":["Y309:2","Y309:3"],"1":"RHzLfUp"},
{"x":1530,"y":554,"d":"L5136A Nrm","i":["Y308:1","Y309:2","Y309:3","Y309:4"],"1":"NHzRtUp"},
{"x":1530,"y":554,"d":"L5136A Rev","i":["Y309:1","Y309:5"],"1":"RHzRtUp"},
{"x":1530,"y":522,"d":"L5136B Nrm","i":["Y308:1","Y309:2","Y309:3","Y309:4"],"1":"NHzLfDn"},
{"x":1530,"y":522,"d":"L5136B Rev","i":["Y309:1","Y309:5"],"1":"RHzLfDn"},
{"x":1258,"y":490,"d":"L5145A Nrm","i":["Y305:4","Y305:5","Y305:6","Y308:5","Y308:6"],"1":"NHzRtDn"},
{"x":1258,"y":490,"d":"L5145A Rev","i":["Y309:6","Y309:7"],"1":"RHzRtDn"},
{"x":1258,"y":522,"d":"L5145B Nrm","i":["Y305:4","Y305:5","Y305:6","Y308:5","Y308:6"],"1":"NHzLfUp"},
{"x":1258,"y":522,"d":"L5145B Rev","i":["Y309:6","Y309:7"],"1":"RHzLfUp"},
{"x":954,"y":522,"d":"L5147A Nrm","i":["Y300:2","Y300:3","Y300:4","Y300:5","Y301:2","Y301:7","Y302:5","Y302:6","Y303:1","Y303:2","Y304:7","Y304:8","Y305:1","Y305:2"],"1":"NHzRtUp"},
{"x":954,"y":522,"d":"L5147A Rev","i":["Y300:6","Y300:7","Y300:8","Y301:1"],"1":"RHzRtUp"},
{"x":954,"y":490,"d":"L5147B Nrm","i":["Y300:2","Y300:3","Y300:4","Y300:5","Y301:2","Y301:7","Y302:5","Y302:6","Y303:1","Y303:2","Y304:7","Y304:8","Y305:1","Y305:2"],"1":"NHzLfDn"},
{"x":954,"y":490,"d":"L5147B Rev","i":["Y300:6","Y300:7","Y300:8","Y301:1"],"1":"RHzLfDn"},
{"x":938,"y":490,"d":"L5148A Nrm","i":["Y300:2","Y300:3","Y300:4","Y300:5","Y300:6","Y300:7","Y300:8","Y301:1","Y301:2","Y301:7","Y302:6","Y303:2","Y303:8","Y305:1","Y305:2"],"1":"NHzRtDn"},
{"x":938,"y":490,"d":"L5148A Rev","i":["Y302:5","Y303:1","Y304:7","Y304:8"],"1":"RHzRtDn"},
{"x":938,"y":522,"d":"L5148B Nrm","i":["Y300:2","Y300:3","Y300:4","Y300:5","Y300:6","Y300:7","Y300:8","Y301:1","Y301:2","Y301:7","Y302:6","Y303:2","Y303:8","Y305:1","Y305:2"],"1":"NHzLfUp"},
{"x":938,"y":522,"d":"L5148B Rev","i":["Y302:5","Y303:1","Y304:7","Y304:8"],"1":"RHzLfUp"},
{"x":922,"y":490,"d":"L5149 Nrm","i":["Y300:6","Y300:7","Y301:7","Y303:8","Y305:1"],"1":"NHzRtUp"},
{"x":922,"y":490,"d":"L5149 Rev","i":["Y300:8","Y301:1","Y301:2","Y305:2"],"1":"RHzRtUp"},
{"x":922,"y":522,"d":"L5150A Nrm","i":["Y300:4","Y300:5","Y302:5","Y302:6","Y303:3","Y304:2","Y304:8","Y305:3"],"1":"NHzRtDn"},
{"x":922,"y":522,"d":"L5150A Rev","i":["Y300:2","Y300:3","Y303:1","Y303:2","Y304:7"],"1":"RHzRtDn"},
{"x":922,"y":554,"d":"L5150B Nrm","i":["Y300:4","Y300:5","Y302:5","Y302:6","Y303:3","Y304:2","Y304:8","Y305:3"],"1":"NHzLfUp"},
{"x":922,"y":554,"d":"L5150B Rev","i":["Y300:2","Y300:3","Y303:1","Y303:2","Y304:7"],"1":"RHzLfUp"},
{"x":938,"y":554,"d":"L5151 Nrm","i":["Y300:2","Y300:3","Y303:1","Y303:2","Y304:7"],"1":"RHzRtDn"},
{"x":938,"y":554,"d":"L5151 Rev","i":["Y303:3","Y305:3"],"1":"NHzRtDn"},
{"x":778,"y":522,"d":"L5153A Nrm","i":["Y300:6","Y301:3","Y301:4","Y301:5","Y301:6","Y301:8","Y303:8","Y304:1","Y305:8","Y306:3","Y306:6","Y306:8"],"1":"NHzRtUp"},
{"x":778,"y":522,"d":"L5153A Rev","i":["Y302:1","Y302:2","Y302:3","Y302:4","Y304:2","Y304:3","Y306:1","Y306:4","Y306:7"],"1":"RHzRtUp"},
{"x":778,"y":490,"d":"L5153B Nrm","i":["Y300:6","Y301:3","Y301:4","Y301:5","Y301:6","Y301:8","Y303:8","Y304:1","Y305:8","Y306:3","Y306:6","Y306:8"],"1":"NHzLfDn"},
{"x":778,"y":490,"d":"L5153B Rev","i":["Y302:1","Y302:2","Y302:3","Y302:4","Y304:2","Y304:3","Y306:1","Y306:4","Y306:7"],"1":"RHzLfDn"},
{"x":714,"y":490,"d":"L5154A Nrm","i":["Y300:6","Y301:3","Y302:1","Y303:8","Y304:1","Y304:2","Y304:3","Y305:7","Y306:2","Y306:5"],"1":"NHzRtUp"},
{"x":714,"y":490,"d":"L5154A Rev","i":["Y301:4","Y301:5","Y301:6","Y302:2","Y302:3","Y302:4","Y305:8","Y306:1","Y306:3","Y306:4","Y306:6","Y306:7"],"1":"RHzRtUp"},
{"x":714,"y":442,"d":"L5154B Nrm","i":["Y300:6","Y301:3","Y302:1","Y303:8","Y304:1","Y304:2","Y304:3","Y305:7","Y306:2","Y306:5"],"1":"NHzLfDn"},
{"x":714,"y":442,"d":"L5154B Rev","i":["Y301:4","Y301:5","Y301:6","Y302:2","Y302:3","Y302:4","Y305:8","Y306:1","Y306:3","Y306:4","Y306:6","Y306:7"],"1":"RHzLfDn"},
{"x":762,"y":586,"d":"L5155A Nrm","i":["Y300:2","Y302:7","Y302:8","Y303:5"],"1":"NHzRtUp"},
{"x":762,"y":586,"d":"L5155A Rev","i":["Y303:4","Y303:6"],"1":"RHzRtUp"},
{"x":762,"y":554,"d":"L5155B Nrm","i":["Y300:2","Y302:7","Y302:8","Y303:5"],"1":"NHzLfDn"},
{"x":762,"y":554,"d":"L5155B Rev","i":["Y303:4","Y303:6"],"1":"RHzLfDn"},
{"x":698,"y":442,"d":"L5156 Nrm","i":["Y301:4","Y302:2","Y305:4","Y306:5","Y306:6","Y306:7"],"1":"NHzRtUp"},
{"x":698,"y":442,"d":"L5156 Rev","i":["Y301:5","Y301:6","Y302:3","Y302:4","Y305:5","Y305:6","Y305:7","Y305:8","Y306:1","Y306:2","Y306:3","Y306:4"],"1":"RHzRtUp"},
{"x":698,"y":410,"d":"L5157 Nrm","i":["Y301:5","Y302:3","Y305:5","Y306:2","Y306:3","Y306:4"],"1":"RVtLfDn"},
{"x":698,"y":410,"d":"L5157 Rev","i":["Y301:6","Y302:4","Y305:6","Y305:7","Y305:8","Y306:1"],"1":"NVtLfDn"},
{"x":634,"y":554,"d":"L5158A Nrm","i":["Y301:8","Y306:8"],"1":"NHzRtUp"},
{"x":634,"y":554,"d":"L5158A Rev","i":["Y303:7","Y307:1"],"1":"RHzRtUp"},
{"x":634,"y":522,"d":"L5158B Nrm","i":["Y301:8","Y306:8"],"1":"NHzLfDn"},
{"x":634,"y":522,"d":"L5158B Rev","i":["Y303:7","Y307:1"],"1":"RHzLfDn"}
],
"conditionals":[
{"i":"L3882","c":["AND","Y254:4","Y271:2"]},
{"i":"L3917_FA","c":["AND","Y32D:5","Y316:3","Y316:5","Y32E:7"]},
{"i":"L3915_FA","c":["AND","Y32E:3","$_L3917_FA"]},
{"i":"L3922_S","c":["AND","Y32E:8","Y316:7"]},
{"i":"L3922_M","c":["AND","Y32E:8",["NOT","$_L3922_S"]]},
{"i":"L3922_R","c":["AND","$_L3922_M","Y345:3"]},
{"i":"L3924_S","c":["AND","Y32F:1","Y317:1"]},
{"i":"L3924_M","c":["AND","Y32F:1",["NOT","$_L3924_S"]]},
{"i":"L3944_R","c":["AND","Y32B:1","Y33B:1"]},
{"i":"L3955_S","c":["AND","Y32B:8",["OR","Y314:1","Y314:3"]]},
{"i":"L3955_M","c":["AND","Y32B:8",["NOT","$_L3955_S"]]},
{"i":"L3957_S","c":["AND","Y32C:2","Y314:6"]},
{"i":"L3957_M","c":["AND","Y32C:2",["NOT","$_L3957_S"]]},
{"i":"L3958_S","c":["AND","Y32C:3","Y314:8"]},
{"i":"L3958_M","c":["AND","Y32C:3",["NOT","$_L3958_S"]]},
{"i":"L3967_S","c":["AND","Y326:5","Y30D:2"]},
{"i":"L3967_M","c":["AND","Y326:5",["NOT","$_L3967_S"]]},
{"i":"L3991_S","c":["AND","Y328:7",["OR","Y30E:8","Y30F:2","Y30F:4"]]},
{"i":"L3991_M","c":["AND","Y328:7",["NOT","$_L3991_S"]]},
{"i":"L3992_S","c":["AND","Y328:8","Y30F:7"]},
{"i":"L3992_M","c":["AND","Y328:8",["NOT","$_L3992_S"]]},
{"i":"L3994_S","c":["AND","Y329:1","Y310:2"]},
{"i":"L3994_M","c":["AND","Y329:1",["NOT","$_L3994_S"]]},
{"i":"L4031_S","c":["AND","Y320:4",["OR","Y300:3","Y300:5","Y300:7","Y301:1"]]},
{"i":"L4031_M","c":["AND","Y320:4",["NOT","$_L4031_S"]]},
{"i":"L4035_S","c":["AND","Y320:8",["OR","Y302:1","Y302:2","Y302:3","Y302:4"]]},
{"i":"L4035_M","c":["AND","Y320:8",["NOT","$_L4035_S"]]},
{"i":"L4036_S","c":["AND","Y321:1","Y302:6"]},
{"i":"L4036_M","c":["AND","Y321:1",["NOT","$_L4036_S"]]},
{"i":"L4037_S","c":["AND","Y321:2","Y302:8"]},
{"i":"L4037_M","c":["AND","Y321:2",["NOT","$_L4037_S"]]},
{"i":"L4038_S","c":["AND","Y321:3",["OR","Y303:2","Y303:3"]]},
{"i":"L4038_M","c":["AND","Y321:3",["NOT","$_L4038_S"]]},
{"i":"L4046_S","c":["AND","Y321:7",["OR","Y304:1","Y304:3"]]},
{"i":"L4046_M","c":["AND","Y321:7",["NOT","$_L4046_S"]]},
{"i":"LH4111_S","c":["AND","HG02:6","HG00:3"]},
{"i":"LH4111_M","c":["AND","HG02:6",["NOT","$_LH4111_S"]]},
{"i":"LH4113_S","c":["AND","HG02:8","HG00:6"]},
{"i":"LH4113_M","c":["AND","HG02:8",["NOT","$_LH4113_S"]]},
{"i":"LH4114_S","c":["AND","HG03:1",["OR","HG00:1","HG00:2"]]},
{"i":"LH4114_M","c":["AND","HG03:1",["NOT","$_LH4114_S"]]}
],
"text":[
{"x":2580,"y":134,"e":"ARTHINGTON\\nVIADUCT","t":"TEXT"},
{"x":2626,"y":238,"e":"BRAMHOPE\\nTUNNEL","t":"TEXT"},
{"x":3208,"y":138,"e":"BURLEY\\nPARK","u":"BUY","t":"LOC"},
{"x":2189,"y":234,"e":"CRIMPLE\\nVIADUCT","t":"TEXT"},
{"x":1786,"y":186,"e":"TO HARROGATE","u":"HGT","t":"MLOC"},
{"x":3052,"y":146,"e":"HEADINGLEY","u":"HDY","t":"LOC"},
{"x":3100,"y":238,"e":"HEADINGLEY\\nTUNNEL","t":"TEXT"},
{"x":2098,"y":138,"e":"HORNBEAM\\nPARK","u":"HBP","t":"LOC"},
{"x":2807,"y":146,"e":"HORSFORTH","u":"HRS","t":"LOC"},
{"x":3474,"y":186,"e":"LEEDS","u":"leedscity","t":"MNAV","g":726,"ga":"L"},
{"x":2296,"y":146,"e":"PANNAL","u":"PNL","t":"LOC"},
{"x":2378,"y":230,"e":"RIGTON\\nMCB-CCTV","t":"TEXT"},
{"x":2472,"y":146,"e":"WEETON","u":"WET","t":"LOC"},
{"x":2492,"y":238,"e":"WESCOEHILL\\nTUNNEL","t":"TEXT"},
{"x":2119,"y":162,"e":"1","t":"TEXT","c":"black"},
{"x":2119,"y":218,"e":"2","t":"TEXT","c":"black"},
{"x":2311,"y":162,"e":"1","t":"TEXT","c":"black"},
{"x":2311,"y":218,"e":"2","t":"TEXT","c":"black"},
{"x":2487,"y":162,"e":"1","t":"TEXT","c":"black"},
{"x":2487,"y":218,"e":"2","t":"TEXT","c":"black"},
{"x":2831,"y":162,"e":"1","t":"TEXT","c":"black"},
{"x":2831,"y":218,"e":"2","t":"TEXT","c":"black"},
{"x":3079,"y":162,"e":"1","t":"TEXT","c":"black"},
{"x":3079,"y":218,"e":"2","t":"TEXT","c":"black"},
{"x":3223,"y":162,"e":"1","t":"TEXT","c":"black"},
{"x":3223,"y":218,"e":"2","t":"TEXT","c":"black"},

{"x":2585,"y":550,"e":"APPERLEY JN","u":"APERLYJ","t":"LOC"},
{"x":2474,"y":458,"e":"APPERLEY\\nBRIDGE","u":"APY","t":"LOC"},
{"x":2435,"y":382,"e":"APPERLEY LANE\\nTUNNEL","t":"TEXT"},
{"x":2341,"y":434,"e":"BAILDON","u":"BLD","t":"LOC"},
{"x":2301,"y":368,"e":"BAILDON TUNNELS","t":"TEXT"},
{"x":2359,"y":384,"e":"1","d":"BAILDON TUNNEL NO. 1","t":"TEXT"},
{"x":2327,"y":384,"e":"2","d":"BAILDON TUNNEL NO. 2","t":"TEXT"},
{"x":1710,"y":290,"e":"BEN RHYDDING","u":"BEY","t":"LOC"},
{"x":1773,"y":466,"e":"BINGLEY","u":"BIY","t":"LOC"},
{"x":1813,"y":558,"e":"BINGLEY\\nTUNNEL","t":"TEXT"},
{"x":1554,"y":694,"e":"BRADFORD\\nFORSTER SQUARE","u":"BDQ","t":"MLOC"},
{"x":592,"y":358,"e":"BROUGHTON ROAD C.S","u":"SKPTBCS","t":"LOC"},
{"x":1828,"y":282,"e":"BURLEY-IN-\\nWHARFEDALE","u":"BUW","t":"LOC"},
{"x":1154,"y":466,"e":"CONONLEY","u":"CEY","t":"LOC"},
{"x":1130,"y":550,"e":"MCB-CCTV","d":"CONONLEY MCB-CCTV","t":"TEXT"},
{"x":1681,"y":466,"e":"CROSSFLATTS","u":"CFL","t":"LOC"},
{"x":2230,"y":550,"e":"DOCKFIELD JN","u":"SHPYDJN","t":"LOC"},
{"x":2159,"y":294,"e":"ESHOLT JN","u":"SHPYESJ","t":"LOC"},
{"x":2264,"y":428,"e":"ESHOLT\\nTUNNEL","t":"TEXT"},
{"x":1897,"y":698,"e":"FRIZINGHALL","u":"FZH","t":"LOC"},
{"x":410,"y":466,"e":"GARGRAVE","u":"GGV","t":"LOC"},
{"x":2073,"y":382,"e":"GREENBOTTOM\\nTUNNEL","t":"TEXT"},
{"x":1978,"y":290,"e":"GUISELEY","u":"GSY","t":"LOC"},
{"x":54,"y":506,"e":"TO HELLIFIELD","u":"HLD","t":"MLOC"},
{"x":1418,"y":282,"e":"ILKLEY","u":"ILK","t":"MLOC"},
{"x":1564,"y":570,"e":"K&WVR","d":"KEIGHLEY & WORTH VALLEY RAILWAY","u":"KEIGWVR","t":"LOC"},
{"x":1258,"y":550,"e":"KILDWICK\\nMCB-CCTV","t":"TEXT"},
{"x":2927,"y":458,"e":"KIRKSTALL\\nFORGE","u":"KLF","t":"LOC"},
{"x":3135,"y":438,"e":"KIRKSTALL UP LOOP","u":"KRKSLUL","t":"LOC"},
{"x":3129,"y":582,"e":"KIRKSTALL DOWN LOOP","u":"KRKSLDL","t":"LOC"},
{"x":1562,"y":466,"e":"KEIGHLEY","u":"KEI","t":"LOC"},
{"x":3474,"y":506,"e":"LEEDS","u":"leedscity","t":"MNAV","g":774,"ga":"L"},
{"x":1909,"y":290,"e":"MENSTON","u":"MNN","t":"LOC"},
{"x":922,"y":590,"e":"RYLSTONE BRANCH","u":"RYLSGBF","t":"LOC"},
{"x":1946,"y":466,"e":"SALTAIRE","u":"SAI","t":"LOC"},
{"x":2088,"y":458,"e":"SHIPLEY","u":"SHY","t":"MLOC"},
{"x":2198,"y":482,"e":"EAST JN","d":"SHIPLEY EAST JN","u":"SHPYEJN","t":"LOC"},
{"x":2017,"y":682,"e":"SOUTH JN","d":"SHIPLEY SOUTH JN","u":"SHPYSJN","t":"LOC"},
{"x":2031,"y":482,"e":"WEST JN","d":"SHIPLEY WEST JN","u":"SHPYWJN","t":"LOC"},
{"x":2001,"y":558,"e":"SHIPLEY\\nTUNNEL","t":"TEXT"},
{"x":808,"y":430,"e":"SKIPTON","u":"SKI","t":"MLOC"},
{"x":2298,"y":334,"e":"SPRINGS JN","u":"SHPYSPJ","t":"LOC"},
{"x":2245,"y":276,"e":"SPRINGS\\nTUNNEL","t":"TEXT"},
{"x":1348,"y":458,"e":"STREETON &\\nSILSDEN","u":"SON","t":"LOC"},
{"x":2370,"y":558,"e":"THACKLEY\\nTUNNEL","t":"TEXT"},
{"x":431,"y":482,"e":"1","t":"TEXT","c":"black"},
{"x":431,"y":538,"e":"2","t":"TEXT","c":"black"},
{"x":844,"y":474,"e":"1","t":"TEXT","c":"black"},
{"x":850,"y":482,"e":"2","t":"TEXT","c":"black"},
{"x":844,"y":538,"e":"3","t":"TEXT","c":"black"},
{"x":850,"y":546,"e":"4","t":"TEXT","c":"black"},
{"x":1175,"y":482,"e":"1","t":"TEXT","c":"black"},
{"x":1175,"y":538,"e":"2","t":"TEXT","c":"black"},
{"x":1375,"y":482,"e":"1","t":"TEXT","c":"black"},
{"x":1375,"y":538,"e":"2","t":"TEXT","c":"black"},
{"x":1451,"y":362,"e":"1","t":"TEXT","c":"black"},
{"x":1451,"y":306,"e":"2","t":"TEXT","c":"black"},
{"x":1587,"y":482,"e":"1","t":"TEXT","c":"black"},
{"x":1583,"y":538,"e":"2","t":"TEXT","c":"black"},
{"x":1632,"y":658,"e":"1","t":"TEXT","c":"black"},
{"x":1638,"y":650,"e":"2","t":"TEXT","c":"black"},
{"x":1635,"y":594,"e":"3","t":"TEXT","c":"black"},
{"x":1711,"y":482,"e":"1","t":"TEXT","c":"black"},
{"x":1711,"y":538,"e":"2","t":"TEXT","c":"black"},
{"x":1743,"y":362,"e":"1","t":"TEXT","c":"black"},
{"x":1743,"y":306,"e":"2","t":"TEXT","c":"black"},
{"x":1791,"y":482,"e":"1","t":"TEXT","c":"black"},
{"x":1791,"y":538,"e":"2","t":"TEXT","c":"black"},
{"x":1855,"y":362,"e":"1","t":"TEXT","c":"black"},
{"x":1855,"y":306,"e":"2","t":"TEXT","c":"black"},
{"x":1927,"y":362,"e":"1","t":"TEXT","c":"black"},
{"x":1927,"y":306,"e":"2","t":"TEXT","c":"black"},
{"x":1927,"y":626,"e":"1","t":"TEXT","c":"black"},
{"x":1927,"y":682,"e":"2","t":"TEXT","c":"black"},
{"x":1967,"y":482,"e":"1","t":"TEXT","c":"black"},
{"x":1967,"y":538,"e":"2","t":"TEXT","c":"black"},
{"x":1999,"y":362,"e":"1","t":"TEXT","c":"black"},
{"x":1999,"y":306,"e":"2","t":"TEXT","c":"black"},
{"x":2127,"y":482,"e":"1","t":"TEXT","c":"black"},
{"x":2127,"y":538,"e":"2","t":"TEXT","c":"black"},
{"x":2127,"y":626,"e":"3","t":"TEXT","c":"black"},
{"x":2127,"y":682,"e":"4","t":"TEXT","c":"black"},
{"x":2138,"y":582,"e":"5","t":"TEXT","c":"black"},
{"x":2487,"y":482,"e":"1","t":"TEXT","c":"black"},
{"x":2503,"y":538,"e":"2","t":"TEXT","c":"black"},
{"x":2951,"y":482,"e":"1","t":"TEXT","c":"black"},
{"x":2951,"y":538,"e":"2","t":"TEXT","c":"black"}
]
}
